<?xml version="1.0" encoding="UTF-8"?>

<FLOW VERSION="3.0" CLEANUP="true">
  <COMMENT></COMMENT>

  <!-- nodes -->

<MAP TIMEOUT="" MODE="STANDALONE">
  <COMMENT>initialize</COMMENT>
  <MAPTARGET>

<Values version="2.0">
  <record name="xml" javaclass="com.wm.util.Values">
    <value name="node_type">record</value>
    <value name="node_subtype">unknown</value>
    <value name="is_public">false</value>
    <value name="field_type">record</value>
    <value name="field_dim">0</value>
    <value name="nillable">true</value>
    <value name="form_qualified">false</value>
    <value name="is_global">false</value>
    <array name="rec_fields" type="record" depth="1">
      <record javaclass="com.wm.util.Values">
        <value name="node_type">record</value>
        <value name="node_subtype">unknown</value>
        <value name="node_comment"></value>
        <record name="node_hints" javaclass="com.wm.util.Values">
          <value name="field_usereditable">true</value>
          <value name="field_largerEditor">false</value>
          <value name="field_password">false</value>
        </record>
        <value name="is_public">false</value>
        <value name="field_name">valueDomainPublicId</value>
        <value name="field_type">string</value>
        <value name="field_dim">0</value>
        <value name="field_opt">true</value>
        <array name="field_options" type="value" depth="1">
        </array>
        <value name="nillable">true</value>
        <value name="form_qualified">false</value>
        <value name="is_global">false</value>
      </record>
      <record javaclass="com.wm.util.Values">
        <value name="node_type">record</value>
        <value name="node_subtype">unknown</value>
        <value name="node_comment"></value>
        <record name="node_hints" javaclass="com.wm.util.Values">
          <value name="field_usereditable">true</value>
          <value name="field_largerEditor">false</value>
          <value name="field_password">false</value>
        </record>
        <value name="is_public">false</value>
        <value name="field_name">valueDomainVersion</value>
        <value name="field_type">string</value>
        <value name="field_dim">0</value>
        <value name="field_opt">true</value>
        <array name="field_options" type="value" depth="1">
        </array>
        <value name="nillable">true</value>
        <value name="form_qualified">false</value>
        <value name="is_global">false</value>
      </record>
      <record javaclass="com.wm.util.Values">
        <value name="node_type">record</value>
        <value name="node_subtype">unknown</value>
        <value name="is_public">false</value>
        <value name="field_name">apiPermissibleValues</value>
        <value name="field_type">recref</value>
        <value name="field_dim">1</value>
        <value name="nillable">true</value>
        <value name="form_qualified">false</value>
        <value name="is_global">false</value>
        <value name="is_soap_array_encoding_used">false</value>
        <value name="modifiable">true</value>
        <value name="rec_ref">NCIAPI.v1_0.docs:PermissibleValue</value>
      </record>
    </array>
    <value name="modifiable">true</value>
  </record>
</Values>
</MAPTARGET>
  <MAPSOURCE>

<Values version="2.0">
  <record name="xml" javaclass="com.wm.util.Values">
    <value name="node_type">record</value>
    <value name="node_subtype">unknown</value>
    <value name="is_public">false</value>
    <value name="field_type">record</value>
    <value name="field_dim">0</value>
    <value name="nillable">true</value>
    <value name="form_qualified">false</value>
    <value name="is_global">false</value>
    <array name="rec_fields" type="record" depth="1">
    </array>
    <value name="modifiable">true</value>
  </record>
</Values>
</MAPSOURCE>

  <!-- nodes -->

<MAPSET NAME="Setter" OVERWRITE="true" VARIABLES="false" GLOBALVARIABLES="false" FIELD="/apiPermissibleValues;4;1;NCIAPI.v1_0.docs:PermissibleValue">
  <DATA ENCODING="XMLValues" I18N="true">

<Values version="2.0">
  <array name="xml" type="record" depth="1">
  </array>
</Values>
</DATA>
</MAPSET>
</MAP>

<INVOKE TIMEOUT="" SERVICE="NCIModel.services:queryPermissibleValueByValueDomain" VALIDATE-IN="$none" VALIDATE-OUT="$none">
  <COMMENT></COMMENT>

  <!-- nodes -->

<MAP MODE="INPUT">
  <MAPTARGET>

<Values version="2.0">
  <record name="xml" javaclass="com.wm.util.Values">
    <value name="node_type">record</value>
    <value name="node_subtype">unknown</value>
    <value name="is_public">false</value>
    <value name="field_type">record</value>
    <value name="field_dim">0</value>
    <value name="wrapper_type">IData</value>
    <value name="nillable">true</value>
    <value name="form_qualified">false</value>
    <value name="is_global">false</value>
    <array name="rec_fields" type="record" depth="1">
      <record javaclass="com.wm.util.Values">
        <value name="node_type">record</value>
        <value name="node_subtype">unknown</value>
        <value name="node_comment"></value>
        <record name="node_hints" javaclass="com.wm.util.Values">
          <value name="field_usereditable">true</value>
          <value name="field_largerEditor">false</value>
          <value name="field_password">false</value>
        </record>
        <value name="is_public">false</value>
        <value name="field_name">valueDomainItemId</value>
        <value name="field_type">string</value>
        <value name="field_dim">0</value>
        <value name="field_opt">true</value>
        <array name="field_options" type="value" depth="1">
        </array>
        <value name="nillable">true</value>
        <value name="form_qualified">false</value>
        <value name="is_global">false</value>
      </record>
      <record javaclass="com.wm.util.Values">
        <value name="node_type">record</value>
        <value name="node_subtype">unknown</value>
        <value name="node_comment"></value>
        <record name="node_hints" javaclass="com.wm.util.Values">
          <value name="field_usereditable">true</value>
          <value name="field_largerEditor">false</value>
          <value name="field_password">false</value>
        </record>
        <value name="is_public">false</value>
        <value name="field_name">valueDomainVersion</value>
        <value name="field_type">string</value>
        <value name="field_dim">0</value>
        <value name="field_opt">true</value>
        <array name="field_options" type="value" depth="1">
        </array>
        <value name="nillable">true</value>
        <value name="form_qualified">false</value>
        <value name="is_global">false</value>
      </record>
    </array>
    <value name="modifiable">true</value>
  </record>
</Values>
</MAPTARGET>
  <MAPSOURCE>

<Values version="2.0">
  <record name="xml" javaclass="com.wm.util.Values">
    <value name="node_type">record</value>
    <value name="node_subtype">unknown</value>
    <value name="is_public">false</value>
    <value name="field_type">record</value>
    <value name="field_dim">0</value>
    <value name="nillable">true</value>
    <value name="form_qualified">false</value>
    <value name="is_global">false</value>
    <array name="rec_fields" type="record" depth="1">
      <record javaclass="com.wm.util.Values">
        <value name="node_type">record</value>
        <value name="node_subtype">unknown</value>
        <value name="node_comment"></value>
        <record name="node_hints" javaclass="com.wm.util.Values">
          <value name="field_usereditable">true</value>
          <value name="field_largerEditor">false</value>
          <value name="field_password">false</value>
        </record>
        <value name="is_public">false</value>
        <value name="field_name">valueDomainPublicId</value>
        <value name="field_type">string</value>
        <value name="field_dim">0</value>
        <value name="field_opt">true</value>
        <array name="field_options" type="value" depth="1">
        </array>
        <value name="nillable">true</value>
        <value name="form_qualified">false</value>
        <value name="is_global">false</value>
      </record>
      <record javaclass="com.wm.util.Values">
        <value name="node_type">record</value>
        <value name="node_subtype">unknown</value>
        <value name="node_comment"></value>
        <record name="node_hints" javaclass="com.wm.util.Values">
          <value name="field_usereditable">true</value>
          <value name="field_largerEditor">false</value>
          <value name="field_password">false</value>
        </record>
        <value name="is_public">false</value>
        <value name="field_name">valueDomainVersion</value>
        <value name="field_type">string</value>
        <value name="field_dim">0</value>
        <value name="field_opt">true</value>
        <array name="field_options" type="value" depth="1">
        </array>
        <value name="nillable">true</value>
        <value name="form_qualified">false</value>
        <value name="is_global">false</value>
      </record>
      <record javaclass="com.wm.util.Values">
        <value name="node_type">record</value>
        <value name="node_subtype">unknown</value>
        <value name="is_public">false</value>
        <value name="field_name">apiPermissibleValues</value>
        <value name="field_type">recref</value>
        <value name="field_dim">1</value>
        <value name="nillable">true</value>
        <value name="form_qualified">false</value>
        <value name="is_global">false</value>
        <value name="is_soap_array_encoding_used">false</value>
        <value name="modifiable">true</value>
        <value name="rec_ref">NCIAPI.v1_0.docs:PermissibleValue</value>
      </record>
    </array>
    <value name="modifiable">true</value>
  </record>
</Values>
</MAPSOURCE>

  <!-- nodes -->

<MAPCOPY FROM="/valueDomainPublicId;1;0" TO="/valueDomainItemId;1;0">
</MAPCOPY>
</MAP>

<MAP MODE="OUTPUT">
  <MAPTARGET>

<Values version="2.0">
  <record name="xml" javaclass="com.wm.util.Values">
    <value name="node_type">record</value>
    <value name="node_subtype">unknown</value>
    <value name="is_public">false</value>
    <value name="field_type">record</value>
    <value name="field_dim">0</value>
    <value name="nillable">true</value>
    <value name="form_qualified">false</value>
    <value name="is_global">false</value>
    <array name="rec_fields" type="record" depth="1">
      <record javaclass="com.wm.util.Values">
        <value name="node_type">unknown</value>
        <value name="node_subtype">unknown</value>
        <value name="is_public">false</value>
        <value name="field_name">valueDomainItemId</value>
        <value name="field_type">string</value>
        <value name="field_dim">0</value>
        <value name="nillable">true</value>
        <value name="form_qualified">false</value>
        <value name="is_global">false</value>
      </record>
      <record javaclass="com.wm.util.Values">
        <value name="node_type">record</value>
        <value name="node_subtype">unknown</value>
        <value name="node_comment"></value>
        <record name="node_hints" javaclass="com.wm.util.Values">
          <value name="field_usereditable">true</value>
          <value name="field_largerEditor">false</value>
          <value name="field_password">false</value>
        </record>
        <value name="is_public">false</value>
        <value name="field_name">valueDomainPublicId</value>
        <value name="field_type">string</value>
        <value name="field_dim">0</value>
        <value name="field_opt">true</value>
        <array name="field_options" type="value" depth="1">
        </array>
        <value name="nillable">true</value>
        <value name="form_qualified">false</value>
        <value name="is_global">false</value>
      </record>
      <record javaclass="com.wm.util.Values">
        <value name="node_type">record</value>
        <value name="node_subtype">unknown</value>
        <value name="node_comment"></value>
        <record name="node_hints" javaclass="com.wm.util.Values">
          <value name="field_usereditable">true</value>
          <value name="field_largerEditor">false</value>
          <value name="field_password">false</value>
        </record>
        <value name="is_public">false</value>
        <value name="field_name">valueDomainVersion</value>
        <value name="field_type">string</value>
        <value name="field_dim">0</value>
        <value name="field_opt">true</value>
        <array name="field_options" type="value" depth="1">
        </array>
        <value name="nillable">true</value>
        <value name="form_qualified">false</value>
        <value name="is_global">false</value>
      </record>
      <record javaclass="com.wm.util.Values">
        <value name="node_type">record</value>
        <value name="node_subtype">unknown</value>
        <value name="is_public">false</value>
        <value name="field_name">apiPermissibleValues</value>
        <value name="field_type">recref</value>
        <value name="field_dim">1</value>
        <value name="nillable">true</value>
        <value name="form_qualified">false</value>
        <value name="is_global">false</value>
        <value name="is_soap_array_encoding_used">false</value>
        <value name="modifiable">true</value>
        <value name="rec_ref">NCIAPI.v1_0.docs:PermissibleValue</value>
      </record>
      <record javaclass="com.wm.util.Values">
        <value name="node_type">unknown</value>
        <value name="node_subtype">unknown</value>
        <value name="node_comment"></value>
        <record name="node_hints" javaclass="com.wm.util.Values">
          <value name="field_usereditable">true</value>
          <value name="field_largerEditor">false</value>
          <value name="field_password">false</value>
        </record>
        <value name="is_public">false</value>
        <value name="field_name">numRecords</value>
        <value name="field_type">string</value>
        <value name="field_dim">0</value>
        <array name="field_options" type="value" depth="1">
        </array>
        <value name="nillable">true</value>
        <value name="form_qualified">false</value>
        <value name="is_global">false</value>
      </record>
      <record javaclass="com.wm.util.Values">
        <value name="node_type">record</value>
        <value name="node_subtype">unknown</value>
        <value name="is_public">false</value>
        <value name="field_name">modelPermissibleValues</value>
        <value name="field_type">recref</value>
        <value name="field_dim">1</value>
        <value name="nillable">true</value>
        <value name="form_qualified">false</value>
        <value name="is_global">false</value>
        <value name="is_soap_array_encoding_used">false</value>
        <value name="modifiable">true</value>
        <value name="rec_ref">NCIModel.docs:PermissibleValue</value>
      </record>
      <record javaclass="com.wm.util.Values">
        <value name="node_type">record</value>
        <value name="node_subtype">unknown</value>
        <value name="node_comment"></value>
        <record name="node_hints" javaclass="com.wm.util.Values">
          <value name="field_largerEditor">false</value>
          <value name="field_password">false</value>
        </record>
        <value name="is_public">false</value>
        <value name="field_name">PermissibleValues</value>
        <value name="field_type">recref</value>
        <value name="field_dim">1</value>
        <value name="wrapper_type">IData</value>
        <value name="nillable">true</value>
        <value name="form_qualified">false</value>
        <value name="is_global">false</value>
        <value name="is_soap_array_encoding_used">false</value>
        <value name="rec_closed">true</value>
        <value name="modifiable">true</value>
        <value name="rec_ref">NCIModel.docs:PermissibleValue</value>
      </record>
    </array>
    <value name="modifiable">true</value>
  </record>
</Values>
</MAPTARGET>
  <MAPSOURCE>

<Values version="2.0">
  <record name="xml" javaclass="com.wm.util.Values">
    <value name="node_type">record</value>
    <value name="node_subtype">unknown</value>
    <value name="is_public">false</value>
    <value name="field_type">record</value>
    <value name="field_dim">0</value>
    <value name="wrapper_type">IData</value>
    <value name="nillable">true</value>
    <value name="form_qualified">false</value>
    <value name="is_global">false</value>
    <array name="rec_fields" type="record" depth="1">
      <record javaclass="com.wm.util.Values">
        <value name="node_type">unknown</value>
        <value name="node_subtype">unknown</value>
        <value name="node_comment"></value>
        <record name="node_hints" javaclass="com.wm.util.Values">
          <value name="field_usereditable">true</value>
          <value name="field_largerEditor">false</value>
          <value name="field_password">false</value>
        </record>
        <value name="is_public">false</value>
        <value name="field_name">numRecords</value>
        <value name="field_type">string</value>
        <value name="field_dim">0</value>
        <array name="field_options" type="value" depth="1">
        </array>
        <value name="nillable">true</value>
        <value name="form_qualified">false</value>
        <value name="is_global">false</value>
      </record>
      <record javaclass="com.wm.util.Values">
        <value name="node_type">record</value>
        <value name="node_subtype">unknown</value>
        <value name="node_comment"></value>
        <record name="node_hints" javaclass="com.wm.util.Values">
          <value name="field_largerEditor">false</value>
          <value name="field_password">false</value>
        </record>
        <value name="is_public">false</value>
        <value name="field_name">PermissibleValues</value>
        <value name="field_type">recref</value>
        <value name="field_dim">1</value>
        <value name="wrapper_type">IData</value>
        <value name="nillable">true</value>
        <value name="form_qualified">false</value>
        <value name="is_global">false</value>
        <value name="is_soap_array_encoding_used">false</value>
        <value name="rec_closed">true</value>
        <value name="modifiable">true</value>
        <value name="rec_ref">NCIModel.docs:PermissibleValue</value>
      </record>
    </array>
    <value name="modifiable">true</value>
  </record>
</Values>
</MAPSOURCE>

  <!-- nodes -->

<MAPCOPY FROM="/PermissibleValues;4;1;NCIModel.docs:PermissibleValue" TO="/modelPermissibleValues;4;1;NCIModel.docs:PermissibleValue">
</MAPCOPY>

<MAPDELETE FIELD="/PermissibleValues;4;1;NCIModel.docs:PermissibleValue">
</MAPDELETE>

<MAPDELETE FIELD="/valueDomainItemId;1;0">
</MAPDELETE>
</MAP>
</INVOKE>

<LOOP TIMEOUT="" IN-ARRAY="/modelPermissibleValues" OUT-ARRAY="/apiPermissibleValues">
  <COMMENT></COMMENT>

  <!-- nodes -->

<MAP TIMEOUT="" MODE="STANDALONE">
  <COMMENT>modelPermissibleValues &gt; apiPermissibleValues</COMMENT>
  <MAPTARGET>

<Values version="2.0">
  <record name="xml" javaclass="com.wm.util.Values">
    <value name="node_type">record</value>
    <value name="node_subtype">unknown</value>
    <value name="is_public">false</value>
    <value name="field_type">record</value>
    <value name="field_dim">0</value>
    <value name="nillable">true</value>
    <value name="form_qualified">false</value>
    <value name="is_global">false</value>
    <array name="rec_fields" type="record" depth="1">
      <record javaclass="com.wm.util.Values">
        <value name="node_type">record</value>
        <value name="node_subtype">unknown</value>
        <value name="node_comment"></value>
        <record name="node_hints" javaclass="com.wm.util.Values">
          <value name="field_usereditable">true</value>
          <value name="field_largerEditor">false</value>
          <value name="field_password">false</value>
        </record>
        <value name="is_public">false</value>
        <value name="field_name">valueDomainPublicId</value>
        <value name="field_type">string</value>
        <value name="field_dim">0</value>
        <value name="field_opt">true</value>
        <array name="field_options" type="value" depth="1">
        </array>
        <value name="nillable">true</value>
        <value name="form_qualified">false</value>
        <value name="is_global">false</value>
      </record>
      <record javaclass="com.wm.util.Values">
        <value name="node_type">record</value>
        <value name="node_subtype">unknown</value>
        <value name="node_comment"></value>
        <record name="node_hints" javaclass="com.wm.util.Values">
          <value name="field_usereditable">true</value>
          <value name="field_largerEditor">false</value>
          <value name="field_password">false</value>
        </record>
        <value name="is_public">false</value>
        <value name="field_name">valueDomainVersion</value>
        <value name="field_type">string</value>
        <value name="field_dim">0</value>
        <value name="field_opt">true</value>
        <array name="field_options" type="value" depth="1">
        </array>
        <value name="nillable">true</value>
        <value name="form_qualified">false</value>
        <value name="is_global">false</value>
      </record>
      <record javaclass="com.wm.util.Values">
        <value name="node_type">record</value>
        <value name="node_subtype">unknown</value>
        <value name="is_public">false</value>
        <value name="field_name">apiPermissibleValues</value>
        <value name="field_type">recref</value>
        <value name="field_dim">0</value>
        <value name="nillable">true</value>
        <value name="form_qualified">false</value>
        <value name="is_global">false</value>
        <value name="modifiable">true</value>
        <value name="rec_ref">NCIAPI.v1_0.docs:PermissibleValue</value>
      </record>
      <record javaclass="com.wm.util.Values">
        <value name="node_type">unknown</value>
        <value name="node_subtype">unknown</value>
        <value name="node_comment"></value>
        <record name="node_hints" javaclass="com.wm.util.Values">
          <value name="field_usereditable">true</value>
          <value name="field_largerEditor">false</value>
          <value name="field_password">false</value>
        </record>
        <value name="is_public">false</value>
        <value name="field_name">numRecords</value>
        <value name="field_type">string</value>
        <value name="field_dim">0</value>
        <array name="field_options" type="value" depth="1">
        </array>
        <value name="nillable">true</value>
        <value name="form_qualified">false</value>
        <value name="is_global">false</value>
      </record>
      <record javaclass="com.wm.util.Values">
        <value name="node_type">record</value>
        <value name="node_subtype">unknown</value>
        <value name="is_public">false</value>
        <value name="field_name">modelPermissibleValues</value>
        <value name="field_type">recref</value>
        <value name="field_dim">0</value>
        <value name="nillable">true</value>
        <value name="form_qualified">false</value>
        <value name="is_global">false</value>
        <value name="modifiable">true</value>
        <value name="rec_ref">NCIModel.docs:PermissibleValue</value>
      </record>
    </array>
    <value name="modifiable">true</value>
  </record>
</Values>
</MAPTARGET>
  <MAPSOURCE>

<Values version="2.0">
  <record name="xml" javaclass="com.wm.util.Values">
    <value name="node_type">record</value>
    <value name="node_subtype">unknown</value>
    <value name="is_public">false</value>
    <value name="field_type">record</value>
    <value name="field_dim">0</value>
    <value name="nillable">true</value>
    <value name="form_qualified">false</value>
    <value name="is_global">false</value>
    <array name="rec_fields" type="record" depth="1">
      <record javaclass="com.wm.util.Values">
        <value name="node_type">record</value>
        <value name="node_subtype">unknown</value>
        <value name="node_comment"></value>
        <record name="node_hints" javaclass="com.wm.util.Values">
          <value name="field_usereditable">true</value>
          <value name="field_largerEditor">false</value>
          <value name="field_password">false</value>
        </record>
        <value name="is_public">false</value>
        <value name="field_name">valueDomainPublicId</value>
        <value name="field_type">string</value>
        <value name="field_dim">0</value>
        <value name="field_opt">true</value>
        <array name="field_options" type="value" depth="1">
        </array>
        <value name="nillable">true</value>
        <value name="form_qualified">false</value>
        <value name="is_global">false</value>
      </record>
      <record javaclass="com.wm.util.Values">
        <value name="node_type">record</value>
        <value name="node_subtype">unknown</value>
        <value name="node_comment"></value>
        <record name="node_hints" javaclass="com.wm.util.Values">
          <value name="field_usereditable">true</value>
          <value name="field_largerEditor">false</value>
          <value name="field_password">false</value>
        </record>
        <value name="is_public">false</value>
        <value name="field_name">valueDomainVersion</value>
        <value name="field_type">string</value>
        <value name="field_dim">0</value>
        <value name="field_opt">true</value>
        <array name="field_options" type="value" depth="1">
        </array>
        <value name="nillable">true</value>
        <value name="form_qualified">false</value>
        <value name="is_global">false</value>
      </record>
      <record javaclass="com.wm.util.Values">
        <value name="node_type">record</value>
        <value name="node_subtype">unknown</value>
        <value name="is_public">false</value>
        <value name="field_name">apiPermissibleValues</value>
        <value name="field_type">recref</value>
        <value name="field_dim">0</value>
        <value name="nillable">true</value>
        <value name="form_qualified">false</value>
        <value name="is_global">false</value>
        <value name="modifiable">true</value>
        <value name="rec_ref">NCIAPI.v1_0.docs:PermissibleValue</value>
      </record>
      <record javaclass="com.wm.util.Values">
        <value name="node_type">unknown</value>
        <value name="node_subtype">unknown</value>
        <value name="node_comment"></value>
        <record name="node_hints" javaclass="com.wm.util.Values">
          <value name="field_usereditable">true</value>
          <value name="field_largerEditor">false</value>
          <value name="field_password">false</value>
        </record>
        <value name="is_public">false</value>
        <value name="field_name">numRecords</value>
        <value name="field_type">string</value>
        <value name="field_dim">0</value>
        <array name="field_options" type="value" depth="1">
        </array>
        <value name="nillable">true</value>
        <value name="form_qualified">false</value>
        <value name="is_global">false</value>
      </record>
      <record javaclass="com.wm.util.Values">
        <value name="node_type">record</value>
        <value name="node_subtype">unknown</value>
        <value name="is_public">false</value>
        <value name="field_name">modelPermissibleValues</value>
        <value name="field_type">recref</value>
        <value name="field_dim">0</value>
        <value name="nillable">true</value>
        <value name="form_qualified">false</value>
        <value name="is_global">false</value>
        <value name="modifiable">true</value>
        <value name="rec_ref">NCIModel.docs:PermissibleValue</value>
      </record>
      <record javaclass="com.wm.util.Values">
        <value name="node_type">unknown</value>
        <value name="node_subtype">unknown</value>
        <value name="is_public">false</value>
        <value name="field_name">$iteration</value>
        <value name="field_type">string</value>
        <value name="field_dim">0</value>
        <value name="nillable">true</value>
        <value name="form_qualified">false</value>
        <value name="is_global">false</value>
      </record>
    </array>
    <value name="modifiable">true</value>
  </record>
</Values>
</MAPSOURCE>

  <!-- nodes -->

<MAPCOPY FROM="/modelPermissibleValues;4;0;NCIModel.docs:PermissibleValue/publicId;1;0" TO="/apiPermissibleValues;4;0;NCIAPI.v1_0.docs:PermissibleValue/publicId;1;0">
</MAPCOPY>

<MAPCOPY FROM="/modelPermissibleValues;4;0;NCIModel.docs:PermissibleValue/valueDescription;1;0" TO="/apiPermissibleValues;4;0;NCIAPI.v1_0.docs:PermissibleValue/valueDescription;1;0">
</MAPCOPY>

<MAPCOPY FROM="/modelPermissibleValues;4;0;NCIModel.docs:PermissibleValue/originName;1;0" TO="/apiPermissibleValues;4;0;NCIAPI.v1_0.docs:PermissibleValue/origin;1;0">
</MAPCOPY>

<MAPCOPY FROM="/modelPermissibleValues;4;0;NCIModel.docs:PermissibleValue/idSeq;1;0" TO="/apiPermissibleValues;4;0;NCIAPI.v1_0.docs:PermissibleValue/id;1;0">
</MAPCOPY>

<MAPCOPY FROM="/modelPermissibleValues;4;0;NCIModel.docs:PermissibleValue/beginDate;1;0" TO="/apiPermissibleValues;4;0;NCIAPI.v1_0.docs:PermissibleValue/beginDate;1;0">
</MAPCOPY>

<MAPCOPY FROM="/modelPermissibleValues;4;0;NCIModel.docs:PermissibleValue/endDate;1;0" TO="/apiPermissibleValues;4;0;NCIAPI.v1_0.docs:PermissibleValue/endDate;1;0">
</MAPCOPY>

<MAPCOPY FROM="/modelPermissibleValues;4;0;NCIModel.docs:PermissibleValue/createdBy;1;0" TO="/apiPermissibleValues;4;0;NCIAPI.v1_0.docs:PermissibleValue/createdBy;1;0">
</MAPCOPY>

<MAPCOPY FROM="/modelPermissibleValues;4;0;NCIModel.docs:PermissibleValue/dateCreated;1;0" TO="/apiPermissibleValues;4;0;NCIAPI.v1_0.docs:PermissibleValue/dateCreated;1;0">
</MAPCOPY>

<MAPCOPY FROM="/modelPermissibleValues;4;0;NCIModel.docs:PermissibleValue/modifiedBy;1;0" TO="/apiPermissibleValues;4;0;NCIAPI.v1_0.docs:PermissibleValue/modifiedBy;1;0">
</MAPCOPY>

<MAPCOPY FROM="/modelPermissibleValues;4;0;NCIModel.docs:PermissibleValue/dateModified;1;0" TO="/apiPermissibleValues;4;0;NCIAPI.v1_0.docs:PermissibleValue/dateModified;1;0">
</MAPCOPY>

<MAPCOPY FROM="/modelPermissibleValues;4;0;NCIModel.docs:PermissibleValue/deletedIndicator;1;0" TO="/apiPermissibleValues;4;0;NCIAPI.v1_0.docs:PermissibleValue/deletedIndicator;1;0">
</MAPCOPY>

<MAPCOPY FROM="/modelPermissibleValues;4;0;NCIModel.docs:PermissibleValue/valueName;1;0" TO="/apiPermissibleValues;4;0;NCIAPI.v1_0.docs:PermissibleValue/value;1;0">
</MAPCOPY>
</MAP>

<INVOKE TIMEOUT="" SERVICE="NCIAPI.v1_0.services:getValueMeaning" VALIDATE-IN="$none" VALIDATE-OUT="$none">
  <COMMENT></COMMENT>

  <!-- nodes -->

<MAP MODE="INPUT">
  <MAPTARGET>

<Values version="2.0">
  <record name="xml" javaclass="com.wm.util.Values">
    <value name="node_type">record</value>
    <value name="node_subtype">unknown</value>
    <value name="is_public">false</value>
    <value name="field_type">record</value>
    <value name="field_dim">0</value>
    <value name="wrapper_type">IData</value>
    <value name="nillable">true</value>
    <value name="form_qualified">false</value>
    <value name="is_global">false</value>
    <array name="rec_fields" type="record" depth="1">
      <record javaclass="com.wm.util.Values">
        <value name="node_type">record</value>
        <value name="node_subtype">unknown</value>
        <value name="node_comment">This is a description for publicID.</value>
        <record name="node_hints" javaclass="com.wm.util.Values">
          <value name="field_usereditable">true</value>
          <value name="field_largerEditor">false</value>
          <value name="field_password">false</value>
        </record>
        <value name="is_public">false</value>
        <value name="field_name">publicId</value>
        <value name="field_type">string</value>
        <value name="field_dim">0</value>
        <array name="field_options" type="value" depth="1">
        </array>
        <value name="nillable">true</value>
        <value name="form_qualified">false</value>
        <value name="is_global">false</value>
      </record>
      <record javaclass="com.wm.util.Values">
        <value name="node_type">record</value>
        <value name="node_subtype">unknown</value>
        <value name="node_comment">Optional. Enter version of Data Element. Default is the latest version.</value>
        <record name="node_hints" javaclass="com.wm.util.Values">
          <value name="field_usereditable">true</value>
          <value name="field_largerEditor">false</value>
          <value name="field_password">false</value>
        </record>
        <value name="is_public">false</value>
        <value name="field_name">version</value>
        <value name="field_type">string</value>
        <value name="field_dim">0</value>
        <array name="field_options" type="value" depth="1">
        </array>
        <value name="nillable">true</value>
        <value name="form_qualified">false</value>
        <value name="is_global">false</value>
      </record>
    </array>
    <value name="modifiable">true</value>
  </record>
</Values>
</MAPTARGET>
  <MAPSOURCE>

<Values version="2.0">
  <record name="xml" javaclass="com.wm.util.Values">
    <value name="node_type">record</value>
    <value name="node_subtype">unknown</value>
    <value name="is_public">false</value>
    <value name="field_type">record</value>
    <value name="field_dim">0</value>
    <value name="nillable">true</value>
    <value name="form_qualified">false</value>
    <value name="is_global">false</value>
    <array name="rec_fields" type="record" depth="1">
      <record javaclass="com.wm.util.Values">
        <value name="node_type">record</value>
        <value name="node_subtype">unknown</value>
        <value name="node_comment"></value>
        <record name="node_hints" javaclass="com.wm.util.Values">
          <value name="field_usereditable">true</value>
          <value name="field_largerEditor">false</value>
          <value name="field_password">false</value>
        </record>
        <value name="is_public">false</value>
        <value name="field_name">valueDomainPublicId</value>
        <value name="field_type">string</value>
        <value name="field_dim">0</value>
        <value name="field_opt">true</value>
        <array name="field_options" type="value" depth="1">
        </array>
        <value name="nillable">true</value>
        <value name="form_qualified">false</value>
        <value name="is_global">false</value>
      </record>
      <record javaclass="com.wm.util.Values">
        <value name="node_type">record</value>
        <value name="node_subtype">unknown</value>
        <value name="node_comment"></value>
        <record name="node_hints" javaclass="com.wm.util.Values">
          <value name="field_usereditable">true</value>
          <value name="field_largerEditor">false</value>
          <value name="field_password">false</value>
        </record>
        <value name="is_public">false</value>
        <value name="field_name">valueDomainVersion</value>
        <value name="field_type">string</value>
        <value name="field_dim">0</value>
        <value name="field_opt">true</value>
        <array name="field_options" type="value" depth="1">
        </array>
        <value name="nillable">true</value>
        <value name="form_qualified">false</value>
        <value name="is_global">false</value>
      </record>
      <record javaclass="com.wm.util.Values">
        <value name="node_type">record</value>
        <value name="node_subtype">unknown</value>
        <value name="is_public">false</value>
        <value name="field_name">apiPermissibleValues</value>
        <value name="field_type">recref</value>
        <value name="field_dim">0</value>
        <value name="nillable">true</value>
        <value name="form_qualified">false</value>
        <value name="is_global">false</value>
        <value name="modifiable">true</value>
        <value name="rec_ref">NCIAPI.v1_0.docs:PermissibleValue</value>
      </record>
      <record javaclass="com.wm.util.Values">
        <value name="node_type">unknown</value>
        <value name="node_subtype">unknown</value>
        <value name="node_comment"></value>
        <record name="node_hints" javaclass="com.wm.util.Values">
          <value name="field_usereditable">true</value>
          <value name="field_largerEditor">false</value>
          <value name="field_password">false</value>
        </record>
        <value name="is_public">false</value>
        <value name="field_name">numRecords</value>
        <value name="field_type">string</value>
        <value name="field_dim">0</value>
        <array name="field_options" type="value" depth="1">
        </array>
        <value name="nillable">true</value>
        <value name="form_qualified">false</value>
        <value name="is_global">false</value>
      </record>
      <record javaclass="com.wm.util.Values">
        <value name="node_type">record</value>
        <value name="node_subtype">unknown</value>
        <value name="is_public">false</value>
        <value name="field_name">modelPermissibleValues</value>
        <value name="field_type">recref</value>
        <value name="field_dim">0</value>
        <value name="nillable">true</value>
        <value name="form_qualified">false</value>
        <value name="is_global">false</value>
        <value name="modifiable">true</value>
        <value name="rec_ref">NCIModel.docs:PermissibleValue</value>
      </record>
      <record javaclass="com.wm.util.Values">
        <value name="node_type">unknown</value>
        <value name="node_subtype">unknown</value>
        <value name="is_public">false</value>
        <value name="field_name">$iteration</value>
        <value name="field_type">string</value>
        <value name="field_dim">0</value>
        <value name="nillable">true</value>
        <value name="form_qualified">false</value>
        <value name="is_global">false</value>
      </record>
    </array>
    <value name="modifiable">true</value>
  </record>
</Values>
</MAPSOURCE>

  <!-- nodes -->

<MAPCOPY FROM="/modelPermissibleValues;4;0;NCIModel.docs:PermissibleValue/valueMeaningVersion;1;0" TO="/version;1;0">
</MAPCOPY>

<MAPCOPY FROM="/modelPermissibleValues;4;0;NCIModel.docs:PermissibleValue/valueMeaningItemId;1;0" TO="/publicId;1;0">
</MAPCOPY>
</MAP>

<MAP MODE="OUTPUT">
  <MAPTARGET>

<Values version="2.0">
  <record name="xml" javaclass="com.wm.util.Values">
    <value name="node_type">record</value>
    <value name="node_subtype">unknown</value>
    <value name="is_public">false</value>
    <value name="field_type">record</value>
    <value name="field_dim">0</value>
    <value name="nillable">true</value>
    <value name="form_qualified">false</value>
    <value name="is_global">false</value>
    <array name="rec_fields" type="record" depth="1">
      <record javaclass="com.wm.util.Values">
        <value name="node_type">unknown</value>
        <value name="node_subtype">unknown</value>
        <value name="is_public">false</value>
        <value name="field_name">publicId</value>
        <value name="field_type">string</value>
        <value name="field_dim">0</value>
        <value name="nillable">true</value>
        <value name="form_qualified">false</value>
        <value name="is_global">false</value>
      </record>
      <record javaclass="com.wm.util.Values">
        <value name="node_type">unknown</value>
        <value name="node_subtype">unknown</value>
        <value name="is_public">false</value>
        <value name="field_name">version</value>
        <value name="field_type">string</value>
        <value name="field_dim">0</value>
        <value name="nillable">true</value>
        <value name="form_qualified">false</value>
        <value name="is_global">false</value>
      </record>
      <record javaclass="com.wm.util.Values">
        <value name="node_type">record</value>
        <value name="node_subtype">unknown</value>
        <value name="node_comment"></value>
        <record name="node_hints" javaclass="com.wm.util.Values">
          <value name="field_usereditable">true</value>
          <value name="field_largerEditor">false</value>
          <value name="field_password">false</value>
        </record>
        <value name="is_public">false</value>
        <value name="field_name">valueDomainPublicId</value>
        <value name="field_type">string</value>
        <value name="field_dim">0</value>
        <value name="field_opt">true</value>
        <array name="field_options" type="value" depth="1">
        </array>
        <value name="nillable">true</value>
        <value name="form_qualified">false</value>
        <value name="is_global">false</value>
      </record>
      <record javaclass="com.wm.util.Values">
        <value name="node_type">record</value>
        <value name="node_subtype">unknown</value>
        <value name="node_comment"></value>
        <record name="node_hints" javaclass="com.wm.util.Values">
          <value name="field_usereditable">true</value>
          <value name="field_largerEditor">false</value>
          <value name="field_password">false</value>
        </record>
        <value name="is_public">false</value>
        <value name="field_name">valueDomainVersion</value>
        <value name="field_type">string</value>
        <value name="field_dim">0</value>
        <value name="field_opt">true</value>
        <array name="field_options" type="value" depth="1">
        </array>
        <value name="nillable">true</value>
        <value name="form_qualified">false</value>
        <value name="is_global">false</value>
      </record>
      <record javaclass="com.wm.util.Values">
        <value name="node_type">record</value>
        <value name="node_subtype">unknown</value>
        <value name="is_public">false</value>
        <value name="field_name">apiPermissibleValues</value>
        <value name="field_type">recref</value>
        <value name="field_dim">0</value>
        <value name="nillable">true</value>
        <value name="form_qualified">false</value>
        <value name="is_global">false</value>
        <value name="modifiable">true</value>
        <value name="rec_ref">NCIAPI.v1_0.docs:PermissibleValue</value>
      </record>
      <record javaclass="com.wm.util.Values">
        <value name="node_type">unknown</value>
        <value name="node_subtype">unknown</value>
        <value name="node_comment"></value>
        <record name="node_hints" javaclass="com.wm.util.Values">
          <value name="field_usereditable">true</value>
          <value name="field_largerEditor">false</value>
          <value name="field_password">false</value>
        </record>
        <value name="is_public">false</value>
        <value name="field_name">numRecords</value>
        <value name="field_type">string</value>
        <value name="field_dim">0</value>
        <array name="field_options" type="value" depth="1">
        </array>
        <value name="nillable">true</value>
        <value name="form_qualified">false</value>
        <value name="is_global">false</value>
      </record>
      <record javaclass="com.wm.util.Values">
        <value name="node_type">record</value>
        <value name="node_subtype">unknown</value>
        <value name="is_public">false</value>
        <value name="field_name">modelPermissibleValues</value>
        <value name="field_type">recref</value>
        <value name="field_dim">0</value>
        <value name="nillable">true</value>
        <value name="form_qualified">false</value>
        <value name="is_global">false</value>
        <value name="modifiable">true</value>
        <value name="rec_ref">NCIModel.docs:PermissibleValue</value>
      </record>
      <record javaclass="com.wm.util.Values">
        <value name="node_type">record</value>
        <value name="node_subtype">unknown</value>
        <value name="node_comment"></value>
        <record name="node_hints" javaclass="com.wm.util.Values">
          <value name="field_largerEditor">false</value>
          <value name="field_password">false</value>
        </record>
        <value name="is_public">false</value>
        <value name="field_name">ValueMeaning</value>
        <value name="field_type">recref</value>
        <value name="field_dim">0</value>
        <value name="wrapper_type">IData</value>
        <value name="nillable">true</value>
        <value name="form_qualified">false</value>
        <value name="is_global">false</value>
        <value name="rec_closed">true</value>
        <value name="modifiable">true</value>
        <value name="rec_ref">NCIAPI.v1_0.docs:ValueMeaning</value>
      </record>
    </array>
    <value name="modifiable">true</value>
  </record>
</Values>
</MAPTARGET>
  <MAPSOURCE>

<Values version="2.0">
  <record name="xml" javaclass="com.wm.util.Values">
    <value name="node_type">record</value>
    <value name="node_subtype">unknown</value>
    <value name="is_public">false</value>
    <value name="field_type">record</value>
    <value name="field_dim">0</value>
    <value name="wrapper_type">IData</value>
    <value name="nillable">true</value>
    <value name="form_qualified">false</value>
    <value name="is_global">false</value>
    <array name="rec_fields" type="record" depth="1">
      <record javaclass="com.wm.util.Values">
        <value name="node_type">record</value>
        <value name="node_subtype">unknown</value>
        <value name="node_comment"></value>
        <record name="node_hints" javaclass="com.wm.util.Values">
          <value name="field_largerEditor">false</value>
          <value name="field_password">false</value>
        </record>
        <value name="is_public">false</value>
        <value name="field_name">ValueMeaning</value>
        <value name="field_type">recref</value>
        <value name="field_dim">0</value>
        <value name="wrapper_type">IData</value>
        <value name="nillable">true</value>
        <value name="form_qualified">false</value>
        <value name="is_global">false</value>
        <value name="rec_closed">true</value>
        <value name="modifiable">true</value>
        <value name="rec_ref">NCIAPI.v1_0.docs:ValueMeaning</value>
      </record>
    </array>
    <value name="modifiable">true</value>
  </record>
</Values>
</MAPSOURCE>

  <!-- nodes -->

<MAPCOPY FROM="/ValueMeaning;4;0;NCIAPI.v1_0.docs:ValueMeaning" TO="/apiPermissibleValues;4;0;NCIAPI.v1_0.docs:PermissibleValue/ValueMeaning;4;0;NCIAPI.v1_0.docs:ValueMeaning">
</MAPCOPY>

<MAPDELETE FIELD="/publicId;1;0">
</MAPDELETE>

<MAPDELETE FIELD="/version;1;0">
</MAPDELETE>

<MAPDELETE FIELD="/ValueMeaning;4;0;NCIAPI.v1_0.docs:ValueMeaning">
</MAPDELETE>
</MAP>
</INVOKE>
</LOOP>

<MAP TIMEOUT="" MODE="STANDALONE">
  <COMMENT>clean</COMMENT>
  <MAPTARGET>

<Values version="2.0">
  <record name="xml" javaclass="com.wm.util.Values">
    <value name="node_type">record</value>
    <value name="node_subtype">unknown</value>
    <value name="is_public">false</value>
    <value name="field_type">record</value>
    <value name="field_dim">0</value>
    <value name="nillable">true</value>
    <value name="form_qualified">false</value>
    <value name="is_global">false</value>
    <array name="rec_fields" type="record" depth="1">
    </array>
    <value name="modifiable">true</value>
  </record>
</Values>
</MAPTARGET>
  <MAPSOURCE>

<Values version="2.0">
  <record name="xml" javaclass="com.wm.util.Values">
    <value name="node_type">record</value>
    <value name="node_subtype">unknown</value>
    <value name="is_public">false</value>
    <value name="field_type">record</value>
    <value name="field_dim">0</value>
    <value name="nillable">true</value>
    <value name="form_qualified">false</value>
    <value name="is_global">false</value>
    <array name="rec_fields" type="record" depth="1">
      <record javaclass="com.wm.util.Values">
        <value name="node_type">record</value>
        <value name="node_subtype">unknown</value>
        <value name="node_comment"></value>
        <record name="node_hints" javaclass="com.wm.util.Values">
          <value name="field_usereditable">true</value>
          <value name="field_largerEditor">false</value>
          <value name="field_password">false</value>
        </record>
        <value name="is_public">false</value>
        <value name="field_name">valueDomainPublicId</value>
        <value name="field_type">string</value>
        <value name="field_dim">0</value>
        <value name="field_opt">true</value>
        <array name="field_options" type="value" depth="1">
        </array>
        <value name="nillable">true</value>
        <value name="form_qualified">false</value>
        <value name="is_global">false</value>
      </record>
      <record javaclass="com.wm.util.Values">
        <value name="node_type">record</value>
        <value name="node_subtype">unknown</value>
        <value name="node_comment"></value>
        <record name="node_hints" javaclass="com.wm.util.Values">
          <value name="field_usereditable">true</value>
          <value name="field_largerEditor">false</value>
          <value name="field_password">false</value>
        </record>
        <value name="is_public">false</value>
        <value name="field_name">valueDomainVersion</value>
        <value name="field_type">string</value>
        <value name="field_dim">0</value>
        <value name="field_opt">true</value>
        <array name="field_options" type="value" depth="1">
        </array>
        <value name="nillable">true</value>
        <value name="form_qualified">false</value>
        <value name="is_global">false</value>
      </record>
      <record javaclass="com.wm.util.Values">
        <value name="node_type">record</value>
        <value name="node_subtype">unknown</value>
        <value name="is_public">false</value>
        <value name="field_name">apiPermissibleValues</value>
        <value name="field_type">recref</value>
        <value name="field_dim">1</value>
        <value name="nillable">true</value>
        <value name="form_qualified">false</value>
        <value name="is_global">false</value>
        <value name="is_soap_array_encoding_used">false</value>
        <value name="modifiable">true</value>
        <value name="rec_ref">NCIAPI.v1_0.docs:PermissibleValue</value>
      </record>
      <record javaclass="com.wm.util.Values">
        <value name="node_type">unknown</value>
        <value name="node_subtype">unknown</value>
        <value name="node_comment"></value>
        <record name="node_hints" javaclass="com.wm.util.Values">
          <value name="field_usereditable">true</value>
          <value name="field_largerEditor">false</value>
          <value name="field_password">false</value>
        </record>
        <value name="is_public">false</value>
        <value name="field_name">numRecords</value>
        <value name="field_type">string</value>
        <value name="field_dim">0</value>
        <array name="field_options" type="value" depth="1">
        </array>
        <value name="nillable">true</value>
        <value name="form_qualified">false</value>
        <value name="is_global">false</value>
      </record>
      <record javaclass="com.wm.util.Values">
        <value name="node_type">record</value>
        <value name="node_subtype">unknown</value>
        <value name="is_public">false</value>
        <value name="field_name">modelPermissibleValues</value>
        <value name="field_type">recref</value>
        <value name="field_dim">1</value>
        <value name="nillable">true</value>
        <value name="form_qualified">false</value>
        <value name="is_global">false</value>
        <value name="is_soap_array_encoding_used">false</value>
        <value name="modifiable">true</value>
        <value name="rec_ref">NCIModel.docs:PermissibleValue</value>
      </record>
    </array>
    <value name="modifiable">true</value>
  </record>
</Values>
</MAPSOURCE>

  <!-- nodes -->

<MAPDELETE FIELD="/modelPermissibleValues;4;1;NCIModel.docs:PermissibleValue">
</MAPDELETE>

<MAPDELETE FIELD="/numRecords;1;0">
</MAPDELETE>
</MAP>

<MAP TIMEOUT="" MODE="STANDALONE">
  <COMMENT>finalize</COMMENT>
  <MAPTARGET>

<Values version="2.0">
  <record name="xml" javaclass="com.wm.util.Values">
    <value name="node_type">record</value>
    <value name="node_subtype">unknown</value>
    <value name="is_public">false</value>
    <value name="field_type">record</value>
    <value name="field_dim">0</value>
    <value name="nillable">true</value>
    <value name="form_qualified">false</value>
    <value name="is_global">false</value>
    <array name="rec_fields" type="record" depth="1">
      <record javaclass="com.wm.util.Values">
        <value name="node_type">record</value>
        <value name="node_subtype">unknown</value>
        <value name="is_public">false</value>
        <value name="field_name">PermissibleValues</value>
        <value name="field_type">recref</value>
        <value name="field_dim">1</value>
        <value name="nillable">true</value>
        <value name="form_qualified">false</value>
        <value name="is_global">false</value>
        <value name="is_soap_array_encoding_used">false</value>
        <value name="modifiable">true</value>
        <value name="rec_ref">NCIAPI.v1_0.docs:PermissibleValue</value>
      </record>
    </array>
    <value name="modifiable">true</value>
  </record>
</Values>
</MAPTARGET>
  <MAPSOURCE>

<Values version="2.0">
  <record name="xml" javaclass="com.wm.util.Values">
    <value name="node_type">record</value>
    <value name="node_subtype">unknown</value>
    <value name="is_public">false</value>
    <value name="field_type">record</value>
    <value name="field_dim">0</value>
    <value name="nillable">true</value>
    <value name="form_qualified">false</value>
    <value name="is_global">false</value>
    <array name="rec_fields" type="record" depth="1">
      <record javaclass="com.wm.util.Values">
        <value name="node_type">record</value>
        <value name="node_subtype">unknown</value>
        <value name="node_comment"></value>
        <record name="node_hints" javaclass="com.wm.util.Values">
          <value name="field_usereditable">true</value>
          <value name="field_largerEditor">false</value>
          <value name="field_password">false</value>
        </record>
        <value name="is_public">false</value>
        <value name="field_name">valueDomainPublicId</value>
        <value name="field_type">string</value>
        <value name="field_dim">0</value>
        <value name="field_opt">true</value>
        <array name="field_options" type="value" depth="1">
        </array>
        <value name="nillable">true</value>
        <value name="form_qualified">false</value>
        <value name="is_global">false</value>
      </record>
      <record javaclass="com.wm.util.Values">
        <value name="node_type">record</value>
        <value name="node_subtype">unknown</value>
        <value name="node_comment"></value>
        <record name="node_hints" javaclass="com.wm.util.Values">
          <value name="field_usereditable">true</value>
          <value name="field_largerEditor">false</value>
          <value name="field_password">false</value>
        </record>
        <value name="is_public">false</value>
        <value name="field_name">valueDomainVersion</value>
        <value name="field_type">string</value>
        <value name="field_dim">0</value>
        <value name="field_opt">true</value>
        <array name="field_options" type="value" depth="1">
        </array>
        <value name="nillable">true</value>
        <value name="form_qualified">false</value>
        <value name="is_global">false</value>
      </record>
      <record javaclass="com.wm.util.Values">
        <value name="node_type">record</value>
        <value name="node_subtype">unknown</value>
        <value name="is_public">false</value>
        <value name="field_name">apiPermissibleValues</value>
        <value name="field_type">recref</value>
        <value name="field_dim">1</value>
        <value name="nillable">true</value>
        <value name="form_qualified">false</value>
        <value name="is_global">false</value>
        <value name="is_soap_array_encoding_used">false</value>
        <value name="modifiable">true</value>
        <value name="rec_ref">NCIAPI.v1_0.docs:PermissibleValue</value>
      </record>
    </array>
    <value name="modifiable">true</value>
  </record>
</Values>
</MAPSOURCE>

  <!-- nodes -->

<MAPDELETE FIELD="/valueDomainPublicId;1;0">
</MAPDELETE>

<MAPDELETE FIELD="/apiPermissibleValues;4;1;NCIAPI.v1_0.docs:PermissibleValue">
</MAPDELETE>

<MAPDELETE FIELD="/valueDomainVersion;1;0">
</MAPDELETE>

<MAPCOPY FROM="/apiPermissibleValues;4;1;NCIAPI.v1_0.docs:PermissibleValue" TO="/PermissibleValues;4;1;NCIAPI.v1_0.docs:PermissibleValue">
</MAPCOPY>
</MAP>
</FLOW>
