<?xml version="1.0" encoding="UTF-8"?>

<FLOW VERSION="3.0" CLEANUP="true">
  <COMMENT></COMMENT>

  <!-- nodes -->

<INVOKE TIMEOUT="" SERVICE="pub.flow:clearPipeline" VALIDATE-IN="$none" VALIDATE-OUT="$none">
  <COMMENT></COMMENT>

  <!-- nodes -->

<MAP MODE="INPUT">
  <MAPTARGET>

<Values version="2.0">
  <record name="xml" javaclass="com.wm.util.Values">
    <value name="node_type">record</value>
    <value name="node_subtype">unknown</value>
    <value name="is_public">false</value>
    <value name="field_name">clearPipelineInput</value>
    <value name="field_type">record</value>
    <value name="field_dim">0</value>
    <value name="nillable">true</value>
    <value name="form_qualified">false</value>
    <value name="is_global">false</value>
    <array name="rec_fields" type="record" depth="1">
      <record javaclass="com.wm.util.Values">
        <value name="node_type">field</value>
        <value name="node_subtype">unknown</value>
        <value name="is_public">false</value>
        <value name="field_name">preserve</value>
        <value name="field_type">string</value>
        <value name="field_dim">1</value>
        <value name="field_opt">true</value>
        <value name="nillable">true</value>
        <value name="form_qualified">false</value>
        <value name="is_global">false</value>
        <value name="is_soap_array_encoding_used">false</value>
      </record>
    </array>
    <value name="modifiable">true</value>
  </record>
</Values>
</MAPTARGET>
  <MAPSOURCE>

<Values version="2.0">
  <record name="xml" javaclass="com.wm.util.Values">
    <value name="node_type">record</value>
    <value name="node_subtype">unknown</value>
    <value name="is_public">false</value>
    <value name="field_type">record</value>
    <value name="field_dim">0</value>
    <value name="nillable">true</value>
    <value name="form_qualified">false</value>
    <value name="is_global">false</value>
    <array name="rec_fields" type="record" depth="1">
    </array>
    <value name="modifiable">true</value>
  </record>
</Values>
</MAPSOURCE>

  <!-- nodes -->

<MAPSET NAME="Setter" OVERWRITE="true" VARIABLES="false" GLOBALVARIABLES="false" FIELD="/preserve;1;1">
  <DATA ENCODING="XMLValues" I18N="true">

<Values version="2.0">
  <array name="xml" type="value" depth="1">
    <value>publicId</value>
    <value>version</value>
  </array>
  <record name="type" javaclass="com.wm.util.Values">
    <value name="node_type">field</value>
    <value name="node_subtype">unknown</value>
    <value name="is_public">false</value>
    <value name="field_name">preserve</value>
    <value name="field_type">string</value>
    <value name="field_dim">1</value>
    <value name="field_opt">true</value>
    <value name="nillable">true</value>
    <value name="form_qualified">false</value>
    <value name="is_global">false</value>
    <value name="is_soap_array_encoding_used">false</value>
  </record>
</Values>
</DATA>
</MAPSET>
</MAP>

<MAP MODE="OUTPUT">
  <MAPTARGET>

<Values version="2.0">
  <record name="xml" javaclass="com.wm.util.Values">
    <value name="node_type">record</value>
    <value name="node_subtype">unknown</value>
    <value name="is_public">false</value>
    <value name="field_type">record</value>
    <value name="field_dim">0</value>
    <value name="nillable">true</value>
    <value name="form_qualified">false</value>
    <value name="is_global">false</value>
    <array name="rec_fields" type="record" depth="1">
      <record javaclass="com.wm.util.Values">
        <value name="node_type">unknown</value>
        <value name="node_subtype">unknown</value>
        <value name="is_public">false</value>
        <value name="field_name">preserve</value>
        <value name="field_type">string</value>
        <value name="field_dim">1</value>
        <value name="nillable">true</value>
        <value name="form_qualified">false</value>
        <value name="is_global">false</value>
        <value name="is_soap_array_encoding_used">false</value>
      </record>
      <record javaclass="com.wm.util.Values">
        <value name="node_type">record</value>
        <value name="node_subtype">unknown</value>
        <value name="node_comment">This is a description for publicID.</value>
        <record name="node_hints" javaclass="com.wm.util.Values">
          <value name="field_usereditable">true</value>
          <value name="field_largerEditor">false</value>
          <value name="field_password">false</value>
        </record>
        <value name="is_public">false</value>
        <value name="field_name">publicId</value>
        <value name="field_type">string</value>
        <value name="field_dim">0</value>
        <array name="field_options" type="value" depth="1">
        </array>
        <value name="nillable">true</value>
        <value name="form_qualified">false</value>
        <value name="is_global">false</value>
      </record>
      <record javaclass="com.wm.util.Values">
        <value name="node_type">record</value>
        <value name="node_subtype">unknown</value>
        <value name="node_comment">Optional. Enter version of Data Element. Default is the latest version.</value>
        <record name="node_hints" javaclass="com.wm.util.Values">
          <value name="field_usereditable">true</value>
          <value name="field_largerEditor">false</value>
          <value name="field_password">false</value>
        </record>
        <value name="is_public">false</value>
        <value name="field_name">version</value>
        <value name="field_type">string</value>
        <value name="field_dim">0</value>
        <array name="field_options" type="value" depth="1">
        </array>
        <value name="nillable">true</value>
        <value name="form_qualified">false</value>
        <value name="is_global">false</value>
      </record>
    </array>
    <value name="modifiable">true</value>
  </record>
</Values>
</MAPTARGET>
  <MAPSOURCE>

<Values version="2.0">
  <record name="xml" javaclass="com.wm.util.Values">
    <value name="node_type">record</value>
    <value name="node_subtype">unknown</value>
    <value name="is_public">false</value>
    <value name="field_type">record</value>
    <value name="field_dim">0</value>
    <value name="nillable">true</value>
    <value name="form_qualified">false</value>
    <value name="is_global">false</value>
    <array name="rec_fields" type="record" depth="1">
    </array>
    <value name="modifiable">true</value>
  </record>
</Values>
</MAPSOURCE>

  <!-- nodes -->

<MAPDELETE FIELD="/preserve;1;1">
</MAPDELETE>
</MAP>
</INVOKE>

<MAP TIMEOUT="" MODE="STANDALONE">
  <COMMENT>initialize</COMMENT>
  <MAPTARGET>

<Values version="2.0">
  <record name="xml" javaclass="com.wm.util.Values">
    <value name="node_type">record</value>
    <value name="node_subtype">unknown</value>
    <value name="is_public">false</value>
    <value name="field_type">record</value>
    <value name="field_dim">0</value>
    <value name="nillable">true</value>
    <value name="form_qualified">false</value>
    <value name="is_global">false</value>
    <array name="rec_fields" type="record" depth="1">
      <record javaclass="com.wm.util.Values">
        <value name="node_type">unknown</value>
        <value name="node_subtype">unknown</value>
        <value name="is_public">false</value>
        <value name="field_name">valueDomainPublicId</value>
        <value name="field_type">string</value>
        <value name="field_dim">0</value>
        <value name="nillable">true</value>
        <value name="form_qualified">false</value>
        <value name="is_global">false</value>
      </record>
      <record javaclass="com.wm.util.Values">
        <value name="node_type">unknown</value>
        <value name="node_subtype">unknown</value>
        <value name="is_public">false</value>
        <value name="field_name">valueDomainVersion</value>
        <value name="field_type">string</value>
        <value name="field_dim">0</value>
        <value name="nillable">true</value>
        <value name="form_qualified">false</value>
        <value name="is_global">false</value>
      </record>
    </array>
    <value name="modifiable">true</value>
  </record>
</Values>
</MAPTARGET>
  <MAPSOURCE>

<Values version="2.0">
  <record name="xml" javaclass="com.wm.util.Values">
    <value name="node_type">record</value>
    <value name="node_subtype">unknown</value>
    <value name="is_public">false</value>
    <value name="field_type">record</value>
    <value name="field_dim">0</value>
    <value name="nillable">true</value>
    <value name="form_qualified">false</value>
    <value name="is_global">false</value>
    <array name="rec_fields" type="record" depth="1">
      <record javaclass="com.wm.util.Values">
        <value name="node_type">record</value>
        <value name="node_subtype">unknown</value>
        <value name="node_comment">This is a description for publicID.</value>
        <record name="node_hints" javaclass="com.wm.util.Values">
          <value name="field_usereditable">true</value>
          <value name="field_largerEditor">false</value>
          <value name="field_password">false</value>
        </record>
        <value name="is_public">false</value>
        <value name="field_name">publicId</value>
        <value name="field_type">string</value>
        <value name="field_dim">0</value>
        <array name="field_options" type="value" depth="1">
        </array>
        <value name="nillable">true</value>
        <value name="form_qualified">false</value>
        <value name="is_global">false</value>
      </record>
      <record javaclass="com.wm.util.Values">
        <value name="node_type">record</value>
        <value name="node_subtype">unknown</value>
        <value name="node_comment">Optional. Enter version of Data Element. Default is the latest version.</value>
        <record name="node_hints" javaclass="com.wm.util.Values">
          <value name="field_usereditable">true</value>
          <value name="field_largerEditor">false</value>
          <value name="field_password">false</value>
        </record>
        <value name="is_public">false</value>
        <value name="field_name">version</value>
        <value name="field_type">string</value>
        <value name="field_dim">0</value>
        <array name="field_options" type="value" depth="1">
        </array>
        <value name="nillable">true</value>
        <value name="form_qualified">false</value>
        <value name="is_global">false</value>
      </record>
    </array>
    <value name="modifiable">true</value>
  </record>
</Values>
</MAPSOURCE>

  <!-- nodes -->

<MAPCOPY FROM="/publicId;1;0" TO="/valueDomainPublicId;1;0">
</MAPCOPY>

<MAPCOPY FROM="/version;1;0" TO="/valueDomainVersion;1;0">
</MAPCOPY>

<MAPDELETE FIELD="/publicId;1;0">
</MAPDELETE>

<MAPDELETE FIELD="/version;1;0">
</MAPDELETE>
</MAP>

<INVOKE TIMEOUT="" SERVICE="NCIModel.services:queryValueDomain" VALIDATE-IN="$none" VALIDATE-OUT="$none">
  <COMMENT></COMMENT>

  <!-- nodes -->

<MAP MODE="INPUT">
  <MAPTARGET>

<Values version="2.0">
  <record name="xml" javaclass="com.wm.util.Values">
    <value name="node_type">record</value>
    <value name="node_subtype">unknown</value>
    <value name="is_public">false</value>
    <value name="field_type">record</value>
    <value name="field_dim">0</value>
    <value name="wrapper_type">IData</value>
    <value name="nillable">true</value>
    <value name="form_qualified">false</value>
    <value name="is_global">false</value>
    <array name="rec_fields" type="record" depth="1">
      <record javaclass="com.wm.util.Values">
        <value name="node_type">record</value>
        <value name="node_subtype">unknown</value>
        <value name="node_comment"></value>
        <record name="node_hints" javaclass="com.wm.util.Values">
          <value name="field_usereditable">true</value>
          <value name="field_largerEditor">false</value>
          <value name="field_password">false</value>
        </record>
        <value name="is_public">false</value>
        <value name="field_name">itemId</value>
        <value name="field_type">string</value>
        <value name="field_dim">0</value>
        <value name="field_opt">true</value>
        <array name="field_options" type="value" depth="1">
        </array>
        <value name="nillable">true</value>
        <value name="form_qualified">false</value>
        <value name="is_global">false</value>
      </record>
      <record javaclass="com.wm.util.Values">
        <value name="node_type">record</value>
        <value name="node_subtype">unknown</value>
        <value name="node_comment"></value>
        <record name="node_hints" javaclass="com.wm.util.Values">
          <value name="field_usereditable">true</value>
          <value name="field_largerEditor">false</value>
          <value name="field_password">false</value>
        </record>
        <value name="is_public">false</value>
        <value name="field_name">version</value>
        <value name="field_type">string</value>
        <value name="field_dim">0</value>
        <value name="field_opt">true</value>
        <array name="field_options" type="value" depth="1">
        </array>
        <value name="nillable">true</value>
        <value name="form_qualified">false</value>
        <value name="is_global">false</value>
      </record>
    </array>
    <value name="modifiable">true</value>
  </record>
</Values>
</MAPTARGET>
  <MAPSOURCE>

<Values version="2.0">
  <record name="xml" javaclass="com.wm.util.Values">
    <value name="node_type">record</value>
    <value name="node_subtype">unknown</value>
    <value name="is_public">false</value>
    <value name="field_type">record</value>
    <value name="field_dim">0</value>
    <value name="nillable">true</value>
    <value name="form_qualified">false</value>
    <value name="is_global">false</value>
    <array name="rec_fields" type="record" depth="1">
      <record javaclass="com.wm.util.Values">
        <value name="node_type">unknown</value>
        <value name="node_subtype">unknown</value>
        <value name="is_public">false</value>
        <value name="field_name">valueDomainPublicId</value>
        <value name="field_type">string</value>
        <value name="field_dim">0</value>
        <value name="nillable">true</value>
        <value name="form_qualified">false</value>
        <value name="is_global">false</value>
      </record>
      <record javaclass="com.wm.util.Values">
        <value name="node_type">unknown</value>
        <value name="node_subtype">unknown</value>
        <value name="is_public">false</value>
        <value name="field_name">valueDomainVersion</value>
        <value name="field_type">string</value>
        <value name="field_dim">0</value>
        <value name="nillable">true</value>
        <value name="form_qualified">false</value>
        <value name="is_global">false</value>
      </record>
    </array>
    <value name="modifiable">true</value>
  </record>
</Values>
</MAPSOURCE>

  <!-- nodes -->

<MAPCOPY FROM="/valueDomainPublicId;1;0" TO="/itemId;1;0">
</MAPCOPY>

<MAPCOPY FROM="/valueDomainVersion;1;0" TO="/version;1;0">
</MAPCOPY>
</MAP>

<MAP MODE="OUTPUT">
  <MAPTARGET>

<Values version="2.0">
  <record name="xml" javaclass="com.wm.util.Values">
    <value name="node_type">record</value>
    <value name="node_subtype">unknown</value>
    <value name="is_public">false</value>
    <value name="field_type">record</value>
    <value name="field_dim">0</value>
    <value name="nillable">true</value>
    <value name="form_qualified">false</value>
    <value name="is_global">false</value>
    <array name="rec_fields" type="record" depth="1">
      <record javaclass="com.wm.util.Values">
        <value name="node_type">unknown</value>
        <value name="node_subtype">unknown</value>
        <value name="is_public">false</value>
        <value name="field_name">itemId</value>
        <value name="field_type">string</value>
        <value name="field_dim">0</value>
        <value name="nillable">true</value>
        <value name="form_qualified">false</value>
        <value name="is_global">false</value>
      </record>
      <record javaclass="com.wm.util.Values">
        <value name="node_type">unknown</value>
        <value name="node_subtype">unknown</value>
        <value name="is_public">false</value>
        <value name="field_name">version</value>
        <value name="field_type">string</value>
        <value name="field_dim">0</value>
        <value name="nillable">true</value>
        <value name="form_qualified">false</value>
        <value name="is_global">false</value>
      </record>
      <record javaclass="com.wm.util.Values">
        <value name="node_type">record</value>
        <value name="node_subtype">unknown</value>
        <value name="is_public">false</value>
        <value name="field_name">ValueDomainResults</value>
        <value name="field_type">recref</value>
        <value name="field_dim">1</value>
        <value name="nillable">true</value>
        <value name="form_qualified">false</value>
        <value name="is_global">false</value>
        <value name="is_soap_array_encoding_used">false</value>
        <value name="modifiable">true</value>
        <value name="rec_ref">NCIModel.docs:ValueDomain</value>
      </record>
      <record javaclass="com.wm.util.Values">
        <value name="node_type">unknown</value>
        <value name="node_subtype">unknown</value>
        <value name="is_public">false</value>
        <value name="field_name">valueDomainPublicId</value>
        <value name="field_type">string</value>
        <value name="field_dim">0</value>
        <value name="nillable">true</value>
        <value name="form_qualified">false</value>
        <value name="is_global">false</value>
      </record>
      <record javaclass="com.wm.util.Values">
        <value name="node_type">unknown</value>
        <value name="node_subtype">unknown</value>
        <value name="is_public">false</value>
        <value name="field_name">valueDomainVersion</value>
        <value name="field_type">string</value>
        <value name="field_dim">0</value>
        <value name="nillable">true</value>
        <value name="form_qualified">false</value>
        <value name="is_global">false</value>
      </record>
      <record javaclass="com.wm.util.Values">
        <value name="node_type">unknown</value>
        <value name="node_subtype">unknown</value>
        <value name="node_comment"></value>
        <record name="node_hints" javaclass="com.wm.util.Values">
          <value name="field_usereditable">true</value>
          <value name="field_largerEditor">false</value>
          <value name="field_password">false</value>
        </record>
        <value name="is_public">false</value>
        <value name="field_name">numRecords</value>
        <value name="field_type">string</value>
        <value name="field_dim">0</value>
        <array name="field_options" type="value" depth="1">
        </array>
        <value name="nillable">true</value>
        <value name="form_qualified">false</value>
        <value name="is_global">false</value>
      </record>
      <record javaclass="com.wm.util.Values">
        <value name="node_type">record</value>
        <value name="node_subtype">unknown</value>
        <value name="node_comment"></value>
        <record name="node_hints" javaclass="com.wm.util.Values">
          <value name="field_largerEditor">false</value>
          <value name="field_password">false</value>
        </record>
        <value name="is_public">false</value>
        <value name="field_name">ValueDomains</value>
        <value name="field_type">recref</value>
        <value name="field_dim">1</value>
        <value name="wrapper_type">IData</value>
        <value name="nillable">true</value>
        <value name="form_qualified">false</value>
        <value name="is_global">false</value>
        <value name="is_soap_array_encoding_used">false</value>
        <value name="rec_closed">true</value>
        <value name="modifiable">true</value>
        <value name="rec_ref">NCIModel.docs:ValueDomain</value>
      </record>
      <record javaclass="com.wm.util.Values">
        <value name="node_type">record</value>
        <value name="node_subtype">unknown</value>
        <value name="is_public">false</value>
        <value name="field_name">modelValueDomain</value>
        <value name="field_type">recref</value>
        <value name="field_dim">0</value>
        <value name="nillable">true</value>
        <value name="form_qualified">false</value>
        <value name="is_global">false</value>
        <value name="modifiable">true</value>
        <value name="rec_ref">NCIModel.docs:ValueDomain</value>
      </record>
    </array>
    <value name="modifiable">true</value>
  </record>
</Values>
</MAPTARGET>
  <MAPSOURCE>

<Values version="2.0">
  <record name="xml" javaclass="com.wm.util.Values">
    <value name="node_type">record</value>
    <value name="node_subtype">unknown</value>
    <value name="is_public">false</value>
    <value name="field_type">record</value>
    <value name="field_dim">0</value>
    <value name="wrapper_type">IData</value>
    <value name="nillable">true</value>
    <value name="form_qualified">false</value>
    <value name="is_global">false</value>
    <array name="rec_fields" type="record" depth="1">
      <record javaclass="com.wm.util.Values">
        <value name="node_type">unknown</value>
        <value name="node_subtype">unknown</value>
        <value name="node_comment"></value>
        <record name="node_hints" javaclass="com.wm.util.Values">
          <value name="field_usereditable">true</value>
          <value name="field_largerEditor">false</value>
          <value name="field_password">false</value>
        </record>
        <value name="is_public">false</value>
        <value name="field_name">numRecords</value>
        <value name="field_type">string</value>
        <value name="field_dim">0</value>
        <array name="field_options" type="value" depth="1">
        </array>
        <value name="nillable">true</value>
        <value name="form_qualified">false</value>
        <value name="is_global">false</value>
      </record>
      <record javaclass="com.wm.util.Values">
        <value name="node_type">record</value>
        <value name="node_subtype">unknown</value>
        <value name="node_comment"></value>
        <record name="node_hints" javaclass="com.wm.util.Values">
          <value name="field_largerEditor">false</value>
          <value name="field_password">false</value>
        </record>
        <value name="is_public">false</value>
        <value name="field_name">ValueDomains</value>
        <value name="field_type">recref</value>
        <value name="field_dim">1</value>
        <value name="wrapper_type">IData</value>
        <value name="nillable">true</value>
        <value name="form_qualified">false</value>
        <value name="is_global">false</value>
        <value name="is_soap_array_encoding_used">false</value>
        <value name="rec_closed">true</value>
        <value name="modifiable">true</value>
        <value name="rec_ref">NCIModel.docs:ValueDomain</value>
      </record>
    </array>
    <value name="modifiable">true</value>
  </record>
</Values>
</MAPSOURCE>

  <!-- nodes -->

<MAPDELETE FIELD="/ValueDomainResults;4;1;NCIModel.docs:ValueDomain">
</MAPDELETE>

<MAPDELETE FIELD="/itemId;1;0">
</MAPDELETE>

<MAPDELETE FIELD="/version;1;0">
</MAPDELETE>

<MAPCOPY FROM="/ValueDomains[0];4;1;NCIModel.docs:ValueDomain" TO="/modelValueDomain;4;0;NCIModel.docs:ValueDomain">
</MAPCOPY>

<MAPDELETE FIELD="/ValueDomains;4;1;NCIModel.docs:ValueDomain">
</MAPDELETE>
</MAP>
</INVOKE>

<BRANCH TIMEOUT="" LABELEXPRESSIONS="true">
  <COMMENT></COMMENT>

  <!-- nodes -->

<SEQUENCE NAME="%numRecords% = 1" TIMEOUT="" EXIT-ON="FAILURE">
  <COMMENT></COMMENT>

  <!-- nodes -->

<MAP TIMEOUT="" MODE="STANDALONE">
  <COMMENT>modelValueDomain &gt; apiValueDomain</COMMENT>
  <MAPTARGET>

<Values version="2.0">
  <record name="xml" javaclass="com.wm.util.Values">
    <value name="node_type">record</value>
    <value name="node_subtype">unknown</value>
    <value name="is_public">false</value>
    <value name="field_type">record</value>
    <value name="field_dim">0</value>
    <value name="nillable">true</value>
    <value name="form_qualified">false</value>
    <value name="is_global">false</value>
    <array name="rec_fields" type="record" depth="1">
      <record javaclass="com.wm.util.Values">
        <value name="node_type">unknown</value>
        <value name="node_subtype">unknown</value>
        <value name="is_public">false</value>
        <value name="field_name">valueDomainPublicId</value>
        <value name="field_type">string</value>
        <value name="field_dim">0</value>
        <value name="nillable">true</value>
        <value name="form_qualified">false</value>
        <value name="is_global">false</value>
      </record>
      <record javaclass="com.wm.util.Values">
        <value name="node_type">unknown</value>
        <value name="node_subtype">unknown</value>
        <value name="is_public">false</value>
        <value name="field_name">valueDomainVersion</value>
        <value name="field_type">string</value>
        <value name="field_dim">0</value>
        <value name="nillable">true</value>
        <value name="form_qualified">false</value>
        <value name="is_global">false</value>
      </record>
      <record javaclass="com.wm.util.Values">
        <value name="node_type">unknown</value>
        <value name="node_subtype">unknown</value>
        <value name="node_comment"></value>
        <record name="node_hints" javaclass="com.wm.util.Values">
          <value name="field_usereditable">true</value>
          <value name="field_largerEditor">false</value>
          <value name="field_password">false</value>
        </record>
        <value name="is_public">false</value>
        <value name="field_name">numRecords</value>
        <value name="field_type">string</value>
        <value name="field_dim">0</value>
        <array name="field_options" type="value" depth="1">
        </array>
        <value name="nillable">true</value>
        <value name="form_qualified">false</value>
        <value name="is_global">false</value>
      </record>
      <record javaclass="com.wm.util.Values">
        <value name="node_type">record</value>
        <value name="node_subtype">unknown</value>
        <value name="is_public">false</value>
        <value name="field_name">modelValueDomain</value>
        <value name="field_type">recref</value>
        <value name="field_dim">0</value>
        <value name="nillable">true</value>
        <value name="form_qualified">false</value>
        <value name="is_global">false</value>
        <value name="modifiable">true</value>
        <value name="rec_ref">NCIModel.docs:ValueDomain</value>
      </record>
      <record javaclass="com.wm.util.Values">
        <value name="node_type">record</value>
        <value name="node_subtype">unknown</value>
        <value name="is_public">false</value>
        <value name="field_name">apiValueDomain</value>
        <value name="field_type">recref</value>
        <value name="field_dim">0</value>
        <value name="nillable">true</value>
        <value name="form_qualified">false</value>
        <value name="is_global">false</value>
        <value name="modifiable">true</value>
        <value name="rec_ref">NCIAPI.v1_0.docs:ValueDomain</value>
      </record>
    </array>
    <value name="modifiable">true</value>
  </record>
</Values>
</MAPTARGET>
  <MAPSOURCE>

<Values version="2.0">
  <record name="xml" javaclass="com.wm.util.Values">
    <value name="node_type">record</value>
    <value name="node_subtype">unknown</value>
    <value name="is_public">false</value>
    <value name="field_type">record</value>
    <value name="field_dim">0</value>
    <value name="nillable">true</value>
    <value name="form_qualified">false</value>
    <value name="is_global">false</value>
    <array name="rec_fields" type="record" depth="1">
      <record javaclass="com.wm.util.Values">
        <value name="node_type">unknown</value>
        <value name="node_subtype">unknown</value>
        <value name="is_public">false</value>
        <value name="field_name">valueDomainPublicId</value>
        <value name="field_type">string</value>
        <value name="field_dim">0</value>
        <value name="nillable">true</value>
        <value name="form_qualified">false</value>
        <value name="is_global">false</value>
      </record>
      <record javaclass="com.wm.util.Values">
        <value name="node_type">unknown</value>
        <value name="node_subtype">unknown</value>
        <value name="is_public">false</value>
        <value name="field_name">valueDomainVersion</value>
        <value name="field_type">string</value>
        <value name="field_dim">0</value>
        <value name="nillable">true</value>
        <value name="form_qualified">false</value>
        <value name="is_global">false</value>
      </record>
      <record javaclass="com.wm.util.Values">
        <value name="node_type">unknown</value>
        <value name="node_subtype">unknown</value>
        <value name="node_comment"></value>
        <record name="node_hints" javaclass="com.wm.util.Values">
          <value name="field_usereditable">true</value>
          <value name="field_largerEditor">false</value>
          <value name="field_password">false</value>
        </record>
        <value name="is_public">false</value>
        <value name="field_name">numRecords</value>
        <value name="field_type">string</value>
        <value name="field_dim">0</value>
        <array name="field_options" type="value" depth="1">
        </array>
        <value name="nillable">true</value>
        <value name="form_qualified">false</value>
        <value name="is_global">false</value>
      </record>
      <record javaclass="com.wm.util.Values">
        <value name="node_type">record</value>
        <value name="node_subtype">unknown</value>
        <value name="is_public">false</value>
        <value name="field_name">modelValueDomain</value>
        <value name="field_type">recref</value>
        <value name="field_dim">0</value>
        <value name="nillable">true</value>
        <value name="form_qualified">false</value>
        <value name="is_global">false</value>
        <value name="modifiable">true</value>
        <value name="rec_ref">NCIModel.docs:ValueDomain</value>
      </record>
    </array>
    <value name="modifiable">true</value>
  </record>
</Values>
</MAPSOURCE>

  <!-- nodes -->

<MAPCOPY FROM="/modelValueDomain;4;0;NCIModel.docs:ValueDomain/itemId;1;0" TO="/apiValueDomain;4;0;NCIAPI.v1_0.docs:ValueDomain/publicId;1;0">
</MAPCOPY>

<MAPCOPY FROM="/modelValueDomain;4;0;NCIModel.docs:ValueDomain/version;1;0" TO="/apiValueDomain;4;0;NCIAPI.v1_0.docs:ValueDomain/version;1;0">
</MAPCOPY>

<MAPCOPY FROM="/modelValueDomain;4;0;NCIModel.docs:ValueDomain/shortName;1;0" TO="/apiValueDomain;4;0;NCIAPI.v1_0.docs:ValueDomain/preferredName;1;0">
</MAPCOPY>

<MAPCOPY FROM="/modelValueDomain;4;0;NCIModel.docs:ValueDomain/longName;1;0" TO="/apiValueDomain;4;0;NCIAPI.v1_0.docs:ValueDomain/longName;1;0">
</MAPCOPY>

<MAPCOPY FROM="/modelValueDomain;4;0;NCIModel.docs:ValueDomain/definition;1;0" TO="/apiValueDomain;4;0;NCIAPI.v1_0.docs:ValueDomain/preferredDefinition;1;0">
</MAPCOPY>

<MAPCOPY FROM="/modelValueDomain;4;0;NCIModel.docs:ValueDomain/contextName;1;0" TO="/apiValueDomain;4;0;NCIAPI.v1_0.docs:ValueDomain/context;1;0">
</MAPCOPY>

<MAPCOPY FROM="/modelValueDomain;4;0;NCIModel.docs:ValueDomain/typeName;1;0" TO="/apiValueDomain;4;0;NCIAPI.v1_0.docs:ValueDomain/type;1;0">
</MAPCOPY>

<MAPCOPY FROM="/modelValueDomain;4;0;NCIModel.docs:ValueDomain/contextVersion;1;0" TO="/apiValueDomain;4;0;NCIAPI.v1_0.docs:ValueDomain/contextVersion;1;0">
</MAPCOPY>

<MAPCOPY FROM="/modelValueDomain;4;0;NCIModel.docs:ValueDomain/dataTypeName;1;0" TO="/apiValueDomain;4;0;NCIAPI.v1_0.docs:ValueDomain/dataType;1;0">
</MAPCOPY>

<MAPCOPY FROM="/modelValueDomain;4;0;NCIModel.docs:ValueDomain/unitOfMeasureName;1;0" TO="/apiValueDomain;4;0;NCIAPI.v1_0.docs:ValueDomain/unitOfMeasure;1;0">
</MAPCOPY>

<MAPCOPY FROM="/modelValueDomain;4;0;NCIModel.docs:ValueDomain/characterSetName;1;0" TO="/apiValueDomain;4;0;NCIAPI.v1_0.docs:ValueDomain/characterSet;1;0">
</MAPCOPY>

<MAPCOPY FROM="/modelValueDomain;4;0;NCIModel.docs:ValueDomain/minLength;1;0" TO="/apiValueDomain;4;0;NCIAPI.v1_0.docs:ValueDomain/minLength;1;0">
</MAPCOPY>

<MAPCOPY FROM="/modelValueDomain;4;0;NCIModel.docs:ValueDomain/maxLength;1;0" TO="/apiValueDomain;4;0;NCIAPI.v1_0.docs:ValueDomain/maxLength;1;0">
</MAPCOPY>

<MAPCOPY FROM="/modelValueDomain;4;0;NCIModel.docs:ValueDomain/minValue;1;0" TO="/apiValueDomain;4;0;NCIAPI.v1_0.docs:ValueDomain/minValue;1;0">
</MAPCOPY>

<MAPCOPY FROM="/modelValueDomain;4;0;NCIModel.docs:ValueDomain/maxValue;1;0" TO="/apiValueDomain;4;0;NCIAPI.v1_0.docs:ValueDomain/maxValue;1;0">
</MAPCOPY>

<MAPCOPY FROM="/modelValueDomain;4;0;NCIModel.docs:ValueDomain/decimalPlace;1;0" TO="/apiValueDomain;4;0;NCIAPI.v1_0.docs:ValueDomain/decimalPlace;1;0">
</MAPCOPY>

<MAPCOPY FROM="/modelValueDomain;4;0;NCIModel.docs:ValueDomain/formatName;1;0" TO="/apiValueDomain;4;0;NCIAPI.v1_0.docs:ValueDomain/format;1;0">
</MAPCOPY>

<MAPCOPY FROM="/modelValueDomain;4;0;NCIModel.docs:ValueDomain/originName;1;0" TO="/apiValueDomain;4;0;NCIAPI.v1_0.docs:ValueDomain/origin;1;0">
</MAPCOPY>

<MAPCOPY FROM="/modelValueDomain;4;0;NCIModel.docs:ValueDomain/workflowStatusName;1;0" TO="/apiValueDomain;4;0;NCIAPI.v1_0.docs:ValueDomain/workflowStatus;1;0">
</MAPCOPY>

<MAPCOPY FROM="/modelValueDomain;4;0;NCIModel.docs:ValueDomain/registrationStatusName;1;0" TO="/apiValueDomain;4;0;NCIAPI.v1_0.docs:ValueDomain/registrationStatus;1;0">
</MAPCOPY>

<MAPCOPY FROM="/modelValueDomain;4;0;NCIModel.docs:ValueDomain/idSeq;1;0" TO="/apiValueDomain;4;0;NCIAPI.v1_0.docs:ValueDomain/id;1;0">
</MAPCOPY>

<MAPCOPY FROM="/modelValueDomain;4;0;NCIModel.docs:ValueDomain/latestVersionIndicator;1;0" TO="/apiValueDomain;4;0;NCIAPI.v1_0.docs:ValueDomain/latestVersionIndicator;1;0">
</MAPCOPY>

<MAPCOPY FROM="/modelValueDomain;4;0;NCIModel.docs:ValueDomain/beginDate;1;0" TO="/apiValueDomain;4;0;NCIAPI.v1_0.docs:ValueDomain/beginDate;1;0">
</MAPCOPY>

<MAPCOPY FROM="/modelValueDomain;4;0;NCIModel.docs:ValueDomain/endDate;1;0" TO="/apiValueDomain;4;0;NCIAPI.v1_0.docs:ValueDomain/endDate;1;0">
</MAPCOPY>

<MAPCOPY FROM="/modelValueDomain;4;0;NCIModel.docs:ValueDomain/createdBy;1;0" TO="/apiValueDomain;4;0;NCIAPI.v1_0.docs:ValueDomain/createdBy;1;0">
</MAPCOPY>

<MAPCOPY FROM="/modelValueDomain;4;0;NCIModel.docs:ValueDomain/dateCreated;1;0" TO="/apiValueDomain;4;0;NCIAPI.v1_0.docs:ValueDomain/dateCreated;1;0">
</MAPCOPY>

<MAPCOPY FROM="/modelValueDomain;4;0;NCIModel.docs:ValueDomain/modifiedBy;1;0" TO="/apiValueDomain;4;0;NCIAPI.v1_0.docs:ValueDomain/modifiedBy;1;0">
</MAPCOPY>

<MAPCOPY FROM="/modelValueDomain;4;0;NCIModel.docs:ValueDomain/dateModified;1;0" TO="/apiValueDomain;4;0;NCIAPI.v1_0.docs:ValueDomain/dateModified;1;0">
</MAPCOPY>

<MAPCOPY FROM="/modelValueDomain;4;0;NCIModel.docs:ValueDomain/administrativeNotes;1;0" TO="/apiValueDomain;4;0;NCIAPI.v1_0.docs:ValueDomain/administrativeNotes;1;0">
</MAPCOPY>

<MAPCOPY FROM="/modelValueDomain;4;0;NCIModel.docs:ValueDomain/deletedIndicator;1;0" TO="/apiValueDomain;4;0;NCIAPI.v1_0.docs:ValueDomain/deletedIndicator;1;0">
</MAPCOPY>

<MAPCOPY FROM="/modelValueDomain;4;0;NCIModel.docs:ValueDomain/unresolvedIssues;1;0" TO="/apiValueDomain;4;0;NCIAPI.v1_0.docs:ValueDomain/unresolvedIssues;1;0">
</MAPCOPY>

<MAPCOPY FROM="/modelValueDomain;4;0;NCIModel.docs:ValueDomain/changeDescription;1;0" TO="/apiValueDomain;4;0;NCIAPI.v1_0.docs:ValueDomain/changeDescription;1;0">
</MAPCOPY>

<MAPCOPY FROM="/modelValueDomain;4;0;NCIModel.docs:ValueDomain/conceptualDomainItemId;1;0" TO="/apiValueDomain;4;0;NCIAPI.v1_0.docs:ValueDomain/ConceptualDomain;4;0;NCIAPI.v1_0.docs:ConceptualDomain/publicId;1;0">
</MAPCOPY>

<MAPCOPY FROM="/modelValueDomain;4;0;NCIModel.docs:ValueDomain/conceptualDomainVersion;1;0" TO="/apiValueDomain;4;0;NCIAPI.v1_0.docs:ValueDomain/ConceptualDomain;4;0;NCIAPI.v1_0.docs:ConceptualDomain/version;1;0">
</MAPCOPY>
</MAP>

<INVOKE TIMEOUT="" SERVICE="NCIAPI.v1_0.services:getPermissibleValueByValueDomain" VALIDATE-IN="$none" VALIDATE-OUT="$none">
  <COMMENT></COMMENT>

  <!-- nodes -->

<MAP MODE="INPUT">
</MAP>

<MAP MODE="OUTPUT">
  <MAPTARGET>

<Values version="2.0">
  <record name="xml" javaclass="com.wm.util.Values">
    <value name="node_type">record</value>
    <value name="node_subtype">unknown</value>
    <value name="is_public">false</value>
    <value name="field_type">record</value>
    <value name="field_dim">0</value>
    <value name="nillable">true</value>
    <value name="form_qualified">false</value>
    <value name="is_global">false</value>
    <array name="rec_fields" type="record" depth="1">
      <record javaclass="com.wm.util.Values">
        <value name="node_type">unknown</value>
        <value name="node_subtype">unknown</value>
        <value name="is_public">false</value>
        <value name="field_name">valueDomainPublicId</value>
        <value name="field_type">string</value>
        <value name="field_dim">0</value>
        <value name="nillable">true</value>
        <value name="form_qualified">false</value>
        <value name="is_global">false</value>
      </record>
      <record javaclass="com.wm.util.Values">
        <value name="node_type">unknown</value>
        <value name="node_subtype">unknown</value>
        <value name="is_public">false</value>
        <value name="field_name">valueDomainVersion</value>
        <value name="field_type">string</value>
        <value name="field_dim">0</value>
        <value name="nillable">true</value>
        <value name="form_qualified">false</value>
        <value name="is_global">false</value>
      </record>
      <record javaclass="com.wm.util.Values">
        <value name="node_type">unknown</value>
        <value name="node_subtype">unknown</value>
        <value name="node_comment"></value>
        <record name="node_hints" javaclass="com.wm.util.Values">
          <value name="field_usereditable">true</value>
          <value name="field_largerEditor">false</value>
          <value name="field_password">false</value>
        </record>
        <value name="is_public">false</value>
        <value name="field_name">numRecords</value>
        <value name="field_type">string</value>
        <value name="field_dim">0</value>
        <array name="field_options" type="value" depth="1">
        </array>
        <value name="nillable">true</value>
        <value name="form_qualified">false</value>
        <value name="is_global">false</value>
      </record>
      <record javaclass="com.wm.util.Values">
        <value name="node_type">record</value>
        <value name="node_subtype">unknown</value>
        <value name="is_public">false</value>
        <value name="field_name">modelValueDomain</value>
        <value name="field_type">recref</value>
        <value name="field_dim">0</value>
        <value name="nillable">true</value>
        <value name="form_qualified">false</value>
        <value name="is_global">false</value>
        <value name="modifiable">true</value>
        <value name="rec_ref">NCIModel.docs:ValueDomain</value>
      </record>
      <record javaclass="com.wm.util.Values">
        <value name="node_type">record</value>
        <value name="node_subtype">unknown</value>
        <value name="is_public">false</value>
        <value name="field_name">apiValueDomain</value>
        <value name="field_type">recref</value>
        <value name="field_dim">0</value>
        <value name="nillable">true</value>
        <value name="form_qualified">false</value>
        <value name="is_global">false</value>
        <value name="modifiable">true</value>
        <value name="rec_ref">NCIAPI.v1_0.docs:ValueDomain</value>
      </record>
      <record javaclass="com.wm.util.Values">
        <value name="node_type">record</value>
        <value name="node_subtype">unknown</value>
        <value name="node_comment"></value>
        <record name="node_hints" javaclass="com.wm.util.Values">
          <value name="field_largerEditor">false</value>
          <value name="field_password">false</value>
        </record>
        <value name="is_public">false</value>
        <value name="field_name">PermissibleValues</value>
        <value name="field_type">recref</value>
        <value name="field_dim">1</value>
        <value name="wrapper_type">IData</value>
        <value name="nillable">true</value>
        <value name="form_qualified">false</value>
        <value name="is_global">false</value>
        <value name="is_soap_array_encoding_used">false</value>
        <value name="rec_closed">true</value>
        <value name="modifiable">true</value>
        <value name="rec_ref">NCIAPI.v1_0.docs:PermissibleValue</value>
      </record>
    </array>
    <value name="modifiable">true</value>
  </record>
</Values>
</MAPTARGET>
  <MAPSOURCE>

<Values version="2.0">
  <record name="xml" javaclass="com.wm.util.Values">
    <value name="node_type">record</value>
    <value name="node_subtype">unknown</value>
    <value name="is_public">false</value>
    <value name="field_type">record</value>
    <value name="field_dim">0</value>
    <value name="wrapper_type">IData</value>
    <value name="nillable">true</value>
    <value name="form_qualified">false</value>
    <value name="is_global">false</value>
    <array name="rec_fields" type="record" depth="1">
      <record javaclass="com.wm.util.Values">
        <value name="node_type">record</value>
        <value name="node_subtype">unknown</value>
        <value name="node_comment"></value>
        <record name="node_hints" javaclass="com.wm.util.Values">
          <value name="field_largerEditor">false</value>
          <value name="field_password">false</value>
        </record>
        <value name="is_public">false</value>
        <value name="field_name">PermissibleValues</value>
        <value name="field_type">recref</value>
        <value name="field_dim">1</value>
        <value name="wrapper_type">IData</value>
        <value name="nillable">true</value>
        <value name="form_qualified">false</value>
        <value name="is_global">false</value>
        <value name="is_soap_array_encoding_used">false</value>
        <value name="rec_closed">true</value>
        <value name="modifiable">true</value>
        <value name="rec_ref">NCIAPI.v1_0.docs:PermissibleValue</value>
      </record>
    </array>
    <value name="modifiable">true</value>
  </record>
</Values>
</MAPSOURCE>

  <!-- nodes -->

<MAPDELETE FIELD="/PermissibleValues;4;1;NCIAPI.v1_0.docs:PermissibleValue">
</MAPDELETE>

<MAPCOPY FROM="/PermissibleValues;4;1;NCIAPI.v1_0.docs:PermissibleValue" TO="/apiValueDomain;4;0;NCIAPI.v1_0.docs:ValueDomain/PermissibleValues;4;1;NCIAPI.v1_0.docs:PermissibleValue">
</MAPCOPY>
</MAP>
</INVOKE>

<INVOKE TIMEOUT="" SERVICE="NCIAPI.v1_0.services:getConceptualDomainByIdVer" VALIDATE-IN="$none" VALIDATE-OUT="$none">
  <COMMENT></COMMENT>

  <!-- nodes -->

<MAP MODE="INPUT">
  <MAPTARGET>

<Values version="2.0">
  <record name="xml" javaclass="com.wm.util.Values">
    <value name="node_type">record</value>
    <value name="node_subtype">unknown</value>
    <value name="is_public">false</value>
    <value name="field_type">record</value>
    <value name="field_dim">0</value>
    <value name="wrapper_type">IData</value>
    <value name="nillable">true</value>
    <value name="form_qualified">false</value>
    <value name="is_global">false</value>
    <array name="rec_fields" type="record" depth="1">
      <record javaclass="com.wm.util.Values">
        <value name="node_type">record</value>
        <value name="node_subtype">unknown</value>
        <value name="node_comment">This is a description for publicID.</value>
        <record name="node_hints" javaclass="com.wm.util.Values">
          <value name="field_usereditable">true</value>
          <value name="field_largerEditor">false</value>
          <value name="field_password">false</value>
        </record>
        <value name="is_public">false</value>
        <value name="field_name">publicId</value>
        <value name="field_type">string</value>
        <value name="field_dim">0</value>
        <array name="field_options" type="value" depth="1">
        </array>
        <value name="nillable">true</value>
        <value name="form_qualified">false</value>
        <value name="is_global">false</value>
      </record>
      <record javaclass="com.wm.util.Values">
        <value name="node_type">record</value>
        <value name="node_subtype">unknown</value>
        <value name="node_comment">Optional. Enter version of Data Element. Default is the latest version.</value>
        <record name="node_hints" javaclass="com.wm.util.Values">
          <value name="field_usereditable">true</value>
          <value name="field_largerEditor">false</value>
          <value name="field_password">false</value>
        </record>
        <value name="is_public">false</value>
        <value name="field_name">version</value>
        <value name="field_type">string</value>
        <value name="field_dim">0</value>
        <array name="field_options" type="value" depth="1">
        </array>
        <value name="nillable">true</value>
        <value name="form_qualified">false</value>
        <value name="is_global">false</value>
      </record>
    </array>
    <value name="modifiable">true</value>
  </record>
</Values>
</MAPTARGET>
  <MAPSOURCE>

<Values version="2.0">
  <record name="xml" javaclass="com.wm.util.Values">
    <value name="node_type">record</value>
    <value name="node_subtype">unknown</value>
    <value name="is_public">false</value>
    <value name="field_type">record</value>
    <value name="field_dim">0</value>
    <value name="nillable">true</value>
    <value name="form_qualified">false</value>
    <value name="is_global">false</value>
    <array name="rec_fields" type="record" depth="1">
      <record javaclass="com.wm.util.Values">
        <value name="node_type">unknown</value>
        <value name="node_subtype">unknown</value>
        <value name="is_public">false</value>
        <value name="field_name">valueDomainPublicId</value>
        <value name="field_type">string</value>
        <value name="field_dim">0</value>
        <value name="nillable">true</value>
        <value name="form_qualified">false</value>
        <value name="is_global">false</value>
      </record>
      <record javaclass="com.wm.util.Values">
        <value name="node_type">unknown</value>
        <value name="node_subtype">unknown</value>
        <value name="is_public">false</value>
        <value name="field_name">valueDomainVersion</value>
        <value name="field_type">string</value>
        <value name="field_dim">0</value>
        <value name="nillable">true</value>
        <value name="form_qualified">false</value>
        <value name="is_global">false</value>
      </record>
      <record javaclass="com.wm.util.Values">
        <value name="node_type">unknown</value>
        <value name="node_subtype">unknown</value>
        <value name="node_comment"></value>
        <record name="node_hints" javaclass="com.wm.util.Values">
          <value name="field_usereditable">true</value>
          <value name="field_largerEditor">false</value>
          <value name="field_password">false</value>
        </record>
        <value name="is_public">false</value>
        <value name="field_name">numRecords</value>
        <value name="field_type">string</value>
        <value name="field_dim">0</value>
        <array name="field_options" type="value" depth="1">
        </array>
        <value name="nillable">true</value>
        <value name="form_qualified">false</value>
        <value name="is_global">false</value>
      </record>
      <record javaclass="com.wm.util.Values">
        <value name="node_type">record</value>
        <value name="node_subtype">unknown</value>
        <value name="is_public">false</value>
        <value name="field_name">modelValueDomain</value>
        <value name="field_type">recref</value>
        <value name="field_dim">0</value>
        <value name="nillable">true</value>
        <value name="form_qualified">false</value>
        <value name="is_global">false</value>
        <value name="modifiable">true</value>
        <value name="rec_ref">NCIModel.docs:ValueDomain</value>
      </record>
      <record javaclass="com.wm.util.Values">
        <value name="node_type">record</value>
        <value name="node_subtype">unknown</value>
        <value name="is_public">false</value>
        <value name="field_name">apiValueDomain</value>
        <value name="field_type">recref</value>
        <value name="field_dim">0</value>
        <value name="nillable">true</value>
        <value name="form_qualified">false</value>
        <value name="is_global">false</value>
        <value name="modifiable">true</value>
        <value name="rec_ref">NCIAPI.v1_0.docs:ValueDomain</value>
      </record>
    </array>
    <value name="modifiable">true</value>
  </record>
</Values>
</MAPSOURCE>

  <!-- nodes -->

<MAPCOPY FROM="/apiValueDomain;4;0;NCIAPI.v1_0.docs:ValueDomain/ConceptualDomain;4;0;NCIAPI.v1_0.docs:ConceptualDomain/publicId;1;0" TO="/publicId;1;0">
</MAPCOPY>

<MAPCOPY FROM="/apiValueDomain;4;0;NCIAPI.v1_0.docs:ValueDomain/ConceptualDomain;4;0;NCIAPI.v1_0.docs:ConceptualDomain/version;1;0" TO="/version;1;0">
</MAPCOPY>
</MAP>

<MAP MODE="OUTPUT">
  <MAPTARGET>

<Values version="2.0">
  <record name="xml" javaclass="com.wm.util.Values">
    <value name="node_type">record</value>
    <value name="node_subtype">unknown</value>
    <value name="is_public">false</value>
    <value name="field_type">record</value>
    <value name="field_dim">0</value>
    <value name="nillable">true</value>
    <value name="form_qualified">false</value>
    <value name="is_global">false</value>
    <array name="rec_fields" type="record" depth="1">
      <record javaclass="com.wm.util.Values">
        <value name="node_type">unknown</value>
        <value name="node_subtype">unknown</value>
        <value name="is_public">false</value>
        <value name="field_name">publicId</value>
        <value name="field_type">string</value>
        <value name="field_dim">0</value>
        <value name="nillable">true</value>
        <value name="form_qualified">false</value>
        <value name="is_global">false</value>
      </record>
      <record javaclass="com.wm.util.Values">
        <value name="node_type">unknown</value>
        <value name="node_subtype">unknown</value>
        <value name="is_public">false</value>
        <value name="field_name">version</value>
        <value name="field_type">string</value>
        <value name="field_dim">0</value>
        <value name="nillable">true</value>
        <value name="form_qualified">false</value>
        <value name="is_global">false</value>
      </record>
      <record javaclass="com.wm.util.Values">
        <value name="node_type">unknown</value>
        <value name="node_subtype">unknown</value>
        <value name="is_public">false</value>
        <value name="field_name">valueDomainPublicId</value>
        <value name="field_type">string</value>
        <value name="field_dim">0</value>
        <value name="nillable">true</value>
        <value name="form_qualified">false</value>
        <value name="is_global">false</value>
      </record>
      <record javaclass="com.wm.util.Values">
        <value name="node_type">unknown</value>
        <value name="node_subtype">unknown</value>
        <value name="is_public">false</value>
        <value name="field_name">valueDomainVersion</value>
        <value name="field_type">string</value>
        <value name="field_dim">0</value>
        <value name="nillable">true</value>
        <value name="form_qualified">false</value>
        <value name="is_global">false</value>
      </record>
      <record javaclass="com.wm.util.Values">
        <value name="node_type">unknown</value>
        <value name="node_subtype">unknown</value>
        <value name="node_comment"></value>
        <record name="node_hints" javaclass="com.wm.util.Values">
          <value name="field_usereditable">true</value>
          <value name="field_largerEditor">false</value>
          <value name="field_password">false</value>
        </record>
        <value name="is_public">false</value>
        <value name="field_name">numRecords</value>
        <value name="field_type">string</value>
        <value name="field_dim">0</value>
        <array name="field_options" type="value" depth="1">
        </array>
        <value name="nillable">true</value>
        <value name="form_qualified">false</value>
        <value name="is_global">false</value>
      </record>
      <record javaclass="com.wm.util.Values">
        <value name="node_type">record</value>
        <value name="node_subtype">unknown</value>
        <value name="is_public">false</value>
        <value name="field_name">modelValueDomain</value>
        <value name="field_type">recref</value>
        <value name="field_dim">0</value>
        <value name="nillable">true</value>
        <value name="form_qualified">false</value>
        <value name="is_global">false</value>
        <value name="modifiable">true</value>
        <value name="rec_ref">NCIModel.docs:ValueDomain</value>
      </record>
      <record javaclass="com.wm.util.Values">
        <value name="node_type">record</value>
        <value name="node_subtype">unknown</value>
        <value name="is_public">false</value>
        <value name="field_name">apiValueDomain</value>
        <value name="field_type">recref</value>
        <value name="field_dim">0</value>
        <value name="nillable">true</value>
        <value name="form_qualified">false</value>
        <value name="is_global">false</value>
        <value name="modifiable">true</value>
        <value name="rec_ref">NCIAPI.v1_0.docs:ValueDomain</value>
      </record>
      <record javaclass="com.wm.util.Values">
        <value name="node_type">record</value>
        <value name="node_subtype">unknown</value>
        <value name="node_comment"></value>
        <record name="node_hints" javaclass="com.wm.util.Values">
          <value name="field_largerEditor">false</value>
          <value name="field_password">false</value>
        </record>
        <value name="is_public">false</value>
        <value name="field_name">ConceptualDomain</value>
        <value name="field_type">recref</value>
        <value name="field_dim">0</value>
        <value name="wrapper_type">IData</value>
        <value name="nillable">true</value>
        <value name="form_qualified">false</value>
        <value name="is_global">false</value>
        <value name="rec_closed">true</value>
        <value name="modifiable">true</value>
        <value name="rec_ref">NCIAPI.v1_0.docs:ConceptualDomain</value>
      </record>
    </array>
    <value name="modifiable">true</value>
  </record>
</Values>
</MAPTARGET>
  <MAPSOURCE>

<Values version="2.0">
  <record name="xml" javaclass="com.wm.util.Values">
    <value name="node_type">record</value>
    <value name="node_subtype">unknown</value>
    <value name="is_public">false</value>
    <value name="field_type">record</value>
    <value name="field_dim">0</value>
    <value name="wrapper_type">IData</value>
    <value name="nillable">true</value>
    <value name="form_qualified">false</value>
    <value name="is_global">false</value>
    <array name="rec_fields" type="record" depth="1">
      <record javaclass="com.wm.util.Values">
        <value name="node_type">record</value>
        <value name="node_subtype">unknown</value>
        <value name="node_comment"></value>
        <record name="node_hints" javaclass="com.wm.util.Values">
          <value name="field_largerEditor">false</value>
          <value name="field_password">false</value>
        </record>
        <value name="is_public">false</value>
        <value name="field_name">ConceptualDomain</value>
        <value name="field_type">recref</value>
        <value name="field_dim">0</value>
        <value name="wrapper_type">IData</value>
        <value name="nillable">true</value>
        <value name="form_qualified">false</value>
        <value name="is_global">false</value>
        <value name="rec_closed">true</value>
        <value name="modifiable">true</value>
        <value name="rec_ref">NCIAPI.v1_0.docs:ConceptualDomain</value>
      </record>
    </array>
    <value name="modifiable">true</value>
  </record>
</Values>
</MAPSOURCE>

  <!-- nodes -->

<MAPDELETE FIELD="/publicId;1;0">
</MAPDELETE>

<MAPDELETE FIELD="/version;1;0">
</MAPDELETE>

<MAPCOPY FROM="/ConceptualDomain;4;0;NCIAPI.v1_0.docs:ConceptualDomain" TO="/apiValueDomain;4;0;NCIAPI.v1_0.docs:ValueDomain/ConceptualDomain;4;0;NCIAPI.v1_0.docs:ConceptualDomain">
</MAPCOPY>

<MAPDELETE FIELD="/ConceptualDomain;4;0;NCIAPI.v1_0.docs:ConceptualDomain">
</MAPDELETE>
</MAP>
</INVOKE>

<INVOKE TIMEOUT="" SERVICE="NCIAPI.v1_0.services:getRepresentationTermByIdVer" VALIDATE-IN="$none" VALIDATE-OUT="$none">
  <COMMENT></COMMENT>

  <!-- nodes -->

<MAP MODE="INPUT">
  <MAPTARGET>

<Values version="2.0">
  <record name="xml" javaclass="com.wm.util.Values">
    <value name="node_type">record</value>
    <value name="node_subtype">unknown</value>
    <value name="is_public">false</value>
    <value name="field_type">record</value>
    <value name="field_dim">0</value>
    <value name="wrapper_type">IData</value>
    <value name="nillable">true</value>
    <value name="form_qualified">false</value>
    <value name="is_global">false</value>
    <array name="rec_fields" type="record" depth="1">
      <record javaclass="com.wm.util.Values">
        <value name="node_type">record</value>
        <value name="node_subtype">unknown</value>
        <value name="node_comment">This is a description for publicID.</value>
        <record name="node_hints" javaclass="com.wm.util.Values">
          <value name="field_usereditable">true</value>
          <value name="field_largerEditor">false</value>
          <value name="field_password">false</value>
        </record>
        <value name="is_public">false</value>
        <value name="field_name">publicId</value>
        <value name="field_type">string</value>
        <value name="field_dim">0</value>
        <array name="field_options" type="value" depth="1">
        </array>
        <value name="nillable">true</value>
        <value name="form_qualified">false</value>
        <value name="is_global">false</value>
      </record>
      <record javaclass="com.wm.util.Values">
        <value name="node_type">record</value>
        <value name="node_subtype">unknown</value>
        <value name="node_comment">Optional. Enter version of Data Element. Default is the latest version.</value>
        <record name="node_hints" javaclass="com.wm.util.Values">
          <value name="field_usereditable">true</value>
          <value name="field_largerEditor">false</value>
          <value name="field_password">false</value>
        </record>
        <value name="is_public">false</value>
        <value name="field_name">version</value>
        <value name="field_type">string</value>
        <value name="field_dim">0</value>
        <array name="field_options" type="value" depth="1">
        </array>
        <value name="nillable">true</value>
        <value name="form_qualified">false</value>
        <value name="is_global">false</value>
      </record>
    </array>
    <value name="modifiable">true</value>
  </record>
</Values>
</MAPTARGET>
  <MAPSOURCE>

<Values version="2.0">
  <record name="xml" javaclass="com.wm.util.Values">
    <value name="node_type">record</value>
    <value name="node_subtype">unknown</value>
    <value name="is_public">false</value>
    <value name="field_type">record</value>
    <value name="field_dim">0</value>
    <value name="nillable">true</value>
    <value name="form_qualified">false</value>
    <value name="is_global">false</value>
    <array name="rec_fields" type="record" depth="1">
      <record javaclass="com.wm.util.Values">
        <value name="node_type">unknown</value>
        <value name="node_subtype">unknown</value>
        <value name="is_public">false</value>
        <value name="field_name">valueDomainPublicId</value>
        <value name="field_type">string</value>
        <value name="field_dim">0</value>
        <value name="nillable">true</value>
        <value name="form_qualified">false</value>
        <value name="is_global">false</value>
      </record>
      <record javaclass="com.wm.util.Values">
        <value name="node_type">unknown</value>
        <value name="node_subtype">unknown</value>
        <value name="is_public">false</value>
        <value name="field_name">valueDomainVersion</value>
        <value name="field_type">string</value>
        <value name="field_dim">0</value>
        <value name="nillable">true</value>
        <value name="form_qualified">false</value>
        <value name="is_global">false</value>
      </record>
      <record javaclass="com.wm.util.Values">
        <value name="node_type">unknown</value>
        <value name="node_subtype">unknown</value>
        <value name="node_comment"></value>
        <record name="node_hints" javaclass="com.wm.util.Values">
          <value name="field_usereditable">true</value>
          <value name="field_largerEditor">false</value>
          <value name="field_password">false</value>
        </record>
        <value name="is_public">false</value>
        <value name="field_name">numRecords</value>
        <value name="field_type">string</value>
        <value name="field_dim">0</value>
        <array name="field_options" type="value" depth="1">
        </array>
        <value name="nillable">true</value>
        <value name="form_qualified">false</value>
        <value name="is_global">false</value>
      </record>
      <record javaclass="com.wm.util.Values">
        <value name="node_type">record</value>
        <value name="node_subtype">unknown</value>
        <value name="is_public">false</value>
        <value name="field_name">modelValueDomain</value>
        <value name="field_type">recref</value>
        <value name="field_dim">0</value>
        <value name="nillable">true</value>
        <value name="form_qualified">false</value>
        <value name="is_global">false</value>
        <value name="modifiable">true</value>
        <value name="rec_ref">NCIModel.docs:ValueDomain</value>
      </record>
      <record javaclass="com.wm.util.Values">
        <value name="node_type">record</value>
        <value name="node_subtype">unknown</value>
        <value name="is_public">false</value>
        <value name="field_name">apiValueDomain</value>
        <value name="field_type">recref</value>
        <value name="field_dim">0</value>
        <value name="nillable">true</value>
        <value name="form_qualified">false</value>
        <value name="is_global">false</value>
        <value name="modifiable">true</value>
        <value name="rec_ref">NCIAPI.v1_0.docs:ValueDomain</value>
      </record>
    </array>
    <value name="modifiable">true</value>
  </record>
</Values>
</MAPSOURCE>

  <!-- nodes -->

<MAPCOPY FROM="/modelValueDomain;4;0;NCIModel.docs:ValueDomain/representationItemId;1;0" TO="/publicId;1;0">
</MAPCOPY>

<MAPCOPY FROM="/modelValueDomain;4;0;NCIModel.docs:ValueDomain/representationVersion;1;0" TO="/version;1;0">
</MAPCOPY>
</MAP>

<MAP MODE="OUTPUT">
  <MAPTARGET>

<Values version="2.0">
  <record name="xml" javaclass="com.wm.util.Values">
    <value name="node_type">record</value>
    <value name="node_subtype">unknown</value>
    <value name="is_public">false</value>
    <value name="field_type">record</value>
    <value name="field_dim">0</value>
    <value name="nillable">true</value>
    <value name="form_qualified">false</value>
    <value name="is_global">false</value>
    <array name="rec_fields" type="record" depth="1">
      <record javaclass="com.wm.util.Values">
        <value name="node_type">unknown</value>
        <value name="node_subtype">unknown</value>
        <value name="is_public">false</value>
        <value name="field_name">publicId</value>
        <value name="field_type">string</value>
        <value name="field_dim">0</value>
        <value name="nillable">true</value>
        <value name="form_qualified">false</value>
        <value name="is_global">false</value>
      </record>
      <record javaclass="com.wm.util.Values">
        <value name="node_type">unknown</value>
        <value name="node_subtype">unknown</value>
        <value name="is_public">false</value>
        <value name="field_name">version</value>
        <value name="field_type">string</value>
        <value name="field_dim">0</value>
        <value name="nillable">true</value>
        <value name="form_qualified">false</value>
        <value name="is_global">false</value>
      </record>
      <record javaclass="com.wm.util.Values">
        <value name="node_type">unknown</value>
        <value name="node_subtype">unknown</value>
        <value name="is_public">false</value>
        <value name="field_name">valueDomainPublicId</value>
        <value name="field_type">string</value>
        <value name="field_dim">0</value>
        <value name="nillable">true</value>
        <value name="form_qualified">false</value>
        <value name="is_global">false</value>
      </record>
      <record javaclass="com.wm.util.Values">
        <value name="node_type">unknown</value>
        <value name="node_subtype">unknown</value>
        <value name="is_public">false</value>
        <value name="field_name">valueDomainVersion</value>
        <value name="field_type">string</value>
        <value name="field_dim">0</value>
        <value name="nillable">true</value>
        <value name="form_qualified">false</value>
        <value name="is_global">false</value>
      </record>
      <record javaclass="com.wm.util.Values">
        <value name="node_type">unknown</value>
        <value name="node_subtype">unknown</value>
        <value name="node_comment"></value>
        <record name="node_hints" javaclass="com.wm.util.Values">
          <value name="field_usereditable">true</value>
          <value name="field_largerEditor">false</value>
          <value name="field_password">false</value>
        </record>
        <value name="is_public">false</value>
        <value name="field_name">numRecords</value>
        <value name="field_type">string</value>
        <value name="field_dim">0</value>
        <array name="field_options" type="value" depth="1">
        </array>
        <value name="nillable">true</value>
        <value name="form_qualified">false</value>
        <value name="is_global">false</value>
      </record>
      <record javaclass="com.wm.util.Values">
        <value name="node_type">record</value>
        <value name="node_subtype">unknown</value>
        <value name="is_public">false</value>
        <value name="field_name">modelValueDomain</value>
        <value name="field_type">recref</value>
        <value name="field_dim">0</value>
        <value name="nillable">true</value>
        <value name="form_qualified">false</value>
        <value name="is_global">false</value>
        <value name="modifiable">true</value>
        <value name="rec_ref">NCIModel.docs:ValueDomain</value>
      </record>
      <record javaclass="com.wm.util.Values">
        <value name="node_type">record</value>
        <value name="node_subtype">unknown</value>
        <value name="is_public">false</value>
        <value name="field_name">apiValueDomain</value>
        <value name="field_type">recref</value>
        <value name="field_dim">0</value>
        <value name="nillable">true</value>
        <value name="form_qualified">false</value>
        <value name="is_global">false</value>
        <value name="modifiable">true</value>
        <value name="rec_ref">NCIAPI.v1_0.docs:ValueDomain</value>
      </record>
      <record javaclass="com.wm.util.Values">
        <value name="node_type">record</value>
        <value name="node_subtype">unknown</value>
        <value name="node_comment"></value>
        <record name="node_hints" javaclass="com.wm.util.Values">
          <value name="field_largerEditor">false</value>
          <value name="field_password">false</value>
        </record>
        <value name="is_public">false</value>
        <value name="field_name">RepresentationTerm</value>
        <value name="field_type">recref</value>
        <value name="field_dim">0</value>
        <value name="wrapper_type">IData</value>
        <value name="nillable">true</value>
        <value name="form_qualified">false</value>
        <value name="is_global">false</value>
        <value name="rec_closed">true</value>
        <value name="modifiable">true</value>
        <value name="rec_ref">NCIAPI.v1_0.docs:RepresentationTerm</value>
      </record>
    </array>
    <value name="modifiable">true</value>
  </record>
</Values>
</MAPTARGET>
  <MAPSOURCE>

<Values version="2.0">
  <record name="xml" javaclass="com.wm.util.Values">
    <value name="node_type">record</value>
    <value name="node_subtype">unknown</value>
    <value name="is_public">false</value>
    <value name="field_type">record</value>
    <value name="field_dim">0</value>
    <value name="wrapper_type">IData</value>
    <value name="nillable">true</value>
    <value name="form_qualified">false</value>
    <value name="is_global">false</value>
    <array name="rec_fields" type="record" depth="1">
      <record javaclass="com.wm.util.Values">
        <value name="node_type">record</value>
        <value name="node_subtype">unknown</value>
        <value name="node_comment"></value>
        <record name="node_hints" javaclass="com.wm.util.Values">
          <value name="field_largerEditor">false</value>
          <value name="field_password">false</value>
        </record>
        <value name="is_public">false</value>
        <value name="field_name">RepresentationTerm</value>
        <value name="field_type">recref</value>
        <value name="field_dim">0</value>
        <value name="wrapper_type">IData</value>
        <value name="nillable">true</value>
        <value name="form_qualified">false</value>
        <value name="is_global">false</value>
        <value name="rec_closed">true</value>
        <value name="modifiable">true</value>
        <value name="rec_ref">NCIAPI.v1_0.docs:RepresentationTerm</value>
      </record>
    </array>
    <value name="modifiable">true</value>
  </record>
</Values>
</MAPSOURCE>

  <!-- nodes -->

<MAPCOPY FROM="/RepresentationTerm;4;0;NCIAPI.v1_0.docs:RepresentationTerm" TO="/apiValueDomain;4;0;NCIAPI.v1_0.docs:ValueDomain/RepresentationTerm;4;0;NCIAPI.v1_0.docs:RepresentationTerm">
</MAPCOPY>
</MAP>
</INVOKE>
</SEQUENCE>
</BRANCH>

<MAP TIMEOUT="" MODE="STANDALONE">
  <COMMENT>clean</COMMENT>
  <MAPTARGET>

<Values version="2.0">
  <record name="xml" javaclass="com.wm.util.Values">
    <value name="node_type">record</value>
    <value name="node_subtype">unknown</value>
    <value name="is_public">false</value>
    <value name="field_type">record</value>
    <value name="field_dim">0</value>
    <value name="nillable">true</value>
    <value name="form_qualified">false</value>
    <value name="is_global">false</value>
    <array name="rec_fields" type="record" depth="1">
    </array>
    <value name="modifiable">true</value>
  </record>
</Values>
</MAPTARGET>
  <MAPSOURCE>

<Values version="2.0">
  <record name="xml" javaclass="com.wm.util.Values">
    <value name="node_type">record</value>
    <value name="node_subtype">unknown</value>
    <value name="is_public">false</value>
    <value name="field_type">record</value>
    <value name="field_dim">0</value>
    <value name="nillable">true</value>
    <value name="form_qualified">false</value>
    <value name="is_global">false</value>
    <array name="rec_fields" type="record" depth="1">
      <record javaclass="com.wm.util.Values">
        <value name="node_type">unknown</value>
        <value name="node_subtype">unknown</value>
        <value name="is_public">false</value>
        <value name="field_name">publicId</value>
        <value name="field_type">string</value>
        <value name="field_dim">0</value>
        <value name="nillable">true</value>
        <value name="form_qualified">false</value>
        <value name="is_global">false</value>
      </record>
      <record javaclass="com.wm.util.Values">
        <value name="node_type">unknown</value>
        <value name="node_subtype">unknown</value>
        <value name="is_public">false</value>
        <value name="field_name">version</value>
        <value name="field_type">string</value>
        <value name="field_dim">0</value>
        <value name="nillable">true</value>
        <value name="form_qualified">false</value>
        <value name="is_global">false</value>
      </record>
      <record javaclass="com.wm.util.Values">
        <value name="node_type">unknown</value>
        <value name="node_subtype">unknown</value>
        <value name="is_public">false</value>
        <value name="field_name">valueDomainPublicId</value>
        <value name="field_type">string</value>
        <value name="field_dim">0</value>
        <value name="nillable">true</value>
        <value name="form_qualified">false</value>
        <value name="is_global">false</value>
      </record>
      <record javaclass="com.wm.util.Values">
        <value name="node_type">unknown</value>
        <value name="node_subtype">unknown</value>
        <value name="is_public">false</value>
        <value name="field_name">valueDomainVersion</value>
        <value name="field_type">string</value>
        <value name="field_dim">0</value>
        <value name="nillable">true</value>
        <value name="form_qualified">false</value>
        <value name="is_global">false</value>
      </record>
      <record javaclass="com.wm.util.Values">
        <value name="node_type">unknown</value>
        <value name="node_subtype">unknown</value>
        <value name="node_comment"></value>
        <record name="node_hints" javaclass="com.wm.util.Values">
          <value name="field_usereditable">true</value>
          <value name="field_largerEditor">false</value>
          <value name="field_password">false</value>
        </record>
        <value name="is_public">false</value>
        <value name="field_name">numRecords</value>
        <value name="field_type">string</value>
        <value name="field_dim">0</value>
        <array name="field_options" type="value" depth="1">
        </array>
        <value name="nillable">true</value>
        <value name="form_qualified">false</value>
        <value name="is_global">false</value>
      </record>
      <record javaclass="com.wm.util.Values">
        <value name="node_type">record</value>
        <value name="node_subtype">unknown</value>
        <value name="is_public">false</value>
        <value name="field_name">modelValueDomain</value>
        <value name="field_type">recref</value>
        <value name="field_dim">0</value>
        <value name="nillable">true</value>
        <value name="form_qualified">false</value>
        <value name="is_global">false</value>
        <value name="modifiable">true</value>
        <value name="rec_ref">NCIModel.docs:ValueDomain</value>
      </record>
      <record javaclass="com.wm.util.Values">
        <value name="node_type">record</value>
        <value name="node_subtype">unknown</value>
        <value name="is_public">false</value>
        <value name="field_name">apiValueDomain</value>
        <value name="field_type">recref</value>
        <value name="field_dim">0</value>
        <value name="nillable">true</value>
        <value name="form_qualified">false</value>
        <value name="is_global">false</value>
        <value name="modifiable">true</value>
        <value name="rec_ref">NCIAPI.v1_0.docs:ValueDomain</value>
      </record>
      <record javaclass="com.wm.util.Values">
        <value name="node_type">record</value>
        <value name="node_subtype">unknown</value>
        <value name="node_comment"></value>
        <record name="node_hints" javaclass="com.wm.util.Values">
          <value name="field_largerEditor">false</value>
          <value name="field_password">false</value>
        </record>
        <value name="is_public">false</value>
        <value name="field_name">RepresentationTerm</value>
        <value name="field_type">recref</value>
        <value name="field_dim">0</value>
        <value name="wrapper_type">IData</value>
        <value name="nillable">true</value>
        <value name="form_qualified">false</value>
        <value name="is_global">false</value>
        <value name="rec_closed">true</value>
        <value name="modifiable">true</value>
        <value name="rec_ref">NCIAPI.v1_0.docs:RepresentationTerm</value>
      </record>
    </array>
    <value name="modifiable">true</value>
  </record>
</Values>
</MAPSOURCE>

  <!-- nodes -->

<MAPDELETE FIELD="/numRecords;1;0">
</MAPDELETE>

<MAPDELETE FIELD="/modelValueDomain;4;0;NCIModel.docs:ValueDomain">
</MAPDELETE>
</MAP>

<MAP TIMEOUT="" MODE="STANDALONE">
  <COMMENT>finalize</COMMENT>
  <MAPTARGET>

<Values version="2.0">
  <record name="xml" javaclass="com.wm.util.Values">
    <value name="node_type">record</value>
    <value name="node_subtype">unknown</value>
    <value name="is_public">false</value>
    <value name="field_type">record</value>
    <value name="field_dim">0</value>
    <value name="nillable">true</value>
    <value name="form_qualified">false</value>
    <value name="is_global">false</value>
    <array name="rec_fields" type="record" depth="1">
      <record javaclass="com.wm.util.Values">
        <value name="node_type">record</value>
        <value name="node_subtype">unknown</value>
        <value name="is_public">false</value>
        <value name="field_name">ValueDomain</value>
        <value name="field_type">recref</value>
        <value name="field_dim">0</value>
        <value name="nillable">true</value>
        <value name="form_qualified">false</value>
        <value name="is_global">false</value>
        <value name="modifiable">true</value>
        <value name="rec_ref">NCIAPI.v1_0.docs:ValueDomain</value>
      </record>
      <record javaclass="com.wm.util.Values">
        <value name="node_type">unknown</value>
        <value name="node_subtype">unknown</value>
        <value name="is_public">false</value>
        <value name="field_name">publicId</value>
        <value name="field_type">string</value>
        <value name="field_dim">0</value>
        <value name="nillable">true</value>
        <value name="form_qualified">false</value>
        <value name="is_global">false</value>
      </record>
      <record javaclass="com.wm.util.Values">
        <value name="node_type">unknown</value>
        <value name="node_subtype">unknown</value>
        <value name="is_public">false</value>
        <value name="field_name">version</value>
        <value name="field_type">string</value>
        <value name="field_dim">0</value>
        <value name="nillable">true</value>
        <value name="form_qualified">false</value>
        <value name="is_global">false</value>
      </record>
      <record javaclass="com.wm.util.Values">
        <value name="node_type">record</value>
        <value name="node_subtype">unknown</value>
        <value name="node_comment"></value>
        <record name="node_hints" javaclass="com.wm.util.Values">
          <value name="field_largerEditor">false</value>
          <value name="field_password">false</value>
        </record>
        <value name="is_public">false</value>
        <value name="field_name">RepresentationTerm</value>
        <value name="field_type">recref</value>
        <value name="field_dim">0</value>
        <value name="wrapper_type">IData</value>
        <value name="nillable">true</value>
        <value name="form_qualified">false</value>
        <value name="is_global">false</value>
        <value name="rec_closed">true</value>
        <value name="modifiable">true</value>
        <value name="rec_ref">NCIAPI.v1_0.docs:RepresentationTerm</value>
      </record>
    </array>
    <value name="modifiable">true</value>
  </record>
</Values>
</MAPTARGET>
  <MAPSOURCE>

<Values version="2.0">
  <record name="xml" javaclass="com.wm.util.Values">
    <value name="node_type">record</value>
    <value name="node_subtype">unknown</value>
    <value name="is_public">false</value>
    <value name="field_type">record</value>
    <value name="field_dim">0</value>
    <value name="nillable">true</value>
    <value name="form_qualified">false</value>
    <value name="is_global">false</value>
    <array name="rec_fields" type="record" depth="1">
      <record javaclass="com.wm.util.Values">
        <value name="node_type">unknown</value>
        <value name="node_subtype">unknown</value>
        <value name="is_public">false</value>
        <value name="field_name">publicId</value>
        <value name="field_type">string</value>
        <value name="field_dim">0</value>
        <value name="nillable">true</value>
        <value name="form_qualified">false</value>
        <value name="is_global">false</value>
      </record>
      <record javaclass="com.wm.util.Values">
        <value name="node_type">unknown</value>
        <value name="node_subtype">unknown</value>
        <value name="is_public">false</value>
        <value name="field_name">version</value>
        <value name="field_type">string</value>
        <value name="field_dim">0</value>
        <value name="nillable">true</value>
        <value name="form_qualified">false</value>
        <value name="is_global">false</value>
      </record>
      <record javaclass="com.wm.util.Values">
        <value name="node_type">unknown</value>
        <value name="node_subtype">unknown</value>
        <value name="is_public">false</value>
        <value name="field_name">valueDomainPublicId</value>
        <value name="field_type">string</value>
        <value name="field_dim">0</value>
        <value name="nillable">true</value>
        <value name="form_qualified">false</value>
        <value name="is_global">false</value>
      </record>
      <record javaclass="com.wm.util.Values">
        <value name="node_type">unknown</value>
        <value name="node_subtype">unknown</value>
        <value name="is_public">false</value>
        <value name="field_name">valueDomainVersion</value>
        <value name="field_type">string</value>
        <value name="field_dim">0</value>
        <value name="nillable">true</value>
        <value name="form_qualified">false</value>
        <value name="is_global">false</value>
      </record>
      <record javaclass="com.wm.util.Values">
        <value name="node_type">record</value>
        <value name="node_subtype">unknown</value>
        <value name="is_public">false</value>
        <value name="field_name">apiValueDomain</value>
        <value name="field_type">recref</value>
        <value name="field_dim">0</value>
        <value name="nillable">true</value>
        <value name="form_qualified">false</value>
        <value name="is_global">false</value>
        <value name="modifiable">true</value>
        <value name="rec_ref">NCIAPI.v1_0.docs:ValueDomain</value>
      </record>
      <record javaclass="com.wm.util.Values">
        <value name="node_type">record</value>
        <value name="node_subtype">unknown</value>
        <value name="node_comment"></value>
        <record name="node_hints" javaclass="com.wm.util.Values">
          <value name="field_largerEditor">false</value>
          <value name="field_password">false</value>
        </record>
        <value name="is_public">false</value>
        <value name="field_name">RepresentationTerm</value>
        <value name="field_type">recref</value>
        <value name="field_dim">0</value>
        <value name="wrapper_type">IData</value>
        <value name="nillable">true</value>
        <value name="form_qualified">false</value>
        <value name="is_global">false</value>
        <value name="rec_closed">true</value>
        <value name="modifiable">true</value>
        <value name="rec_ref">NCIAPI.v1_0.docs:RepresentationTerm</value>
      </record>
    </array>
    <value name="modifiable">true</value>
  </record>
</Values>
</MAPSOURCE>

  <!-- nodes -->

<MAPCOPY FROM="/apiValueDomain;4;0;NCIAPI.v1_0.docs:ValueDomain" TO="/ValueDomain;4;0;NCIAPI.v1_0.docs:ValueDomain">
</MAPCOPY>

<MAPDELETE FIELD="/valueDomainPublicId;1;0">
</MAPDELETE>

<MAPDELETE FIELD="/valueDomainVersion;1;0">
</MAPDELETE>

<MAPDELETE FIELD="/apiValueDomain;4;0;NCIAPI.v1_0.docs:ValueDomain">
</MAPDELETE>
</MAP>
</FLOW>
